[{"排名":"1","代號":"6223","名稱":"旺矽","市場":"櫃","成交":"154","漲跌價":"+8","漲跌幅":"+5.48","成交張數":"34561","法人買賣日期":"08\/19","外資買進金額":"740","外資賣出金額":"749","外資買賣超金額":"-9.24","投信買進金額":"676","投信賣出金額":"0","投信買賣超金額":"+676","自營買進金額":"62.2","自營賣出金額":"43.5","自營買賣超金額":"+18.7","合計買進金額":"1479","合計賣出金額":"793","合計買賣超金額":"+686","法人買賣超註記":"－  ＋  ＋"},{"排名":"2","代號":"2383","名稱":"台光電","市場":"市","成交":"228","漲跌價":"+5.5","漲跌幅":"+2.47","成交張數":"9510","法人買賣日期":"08\/19","外資買進金額":"829","外資賣出金額":"747","外資買賣超金額":"+82.1","投信買進金額":"565","投信賣出金額":"62.6","投信買賣超金額":"+503","自營買進金額":"108","自營賣出金額":"182","自營買賣超金額":"-73.8","合計買進金額":"1502","合計賣出金額":"991","合計買賣超金額":"+511","法人買賣超註記":"＋  ＋  －"},{"排名":"3","代號":"6271","名稱":"同欣電","市場":"市","成交":"239","漲跌價":"-14.5","漲跌幅":"-5.72","成交張數":"11521","法人買賣日期":"08\/19","外資買進金額":"491","外資賣出金額":"835","外資買賣超金額":"-343","投信買進金額":"440","投信賣出金額":"0","投信買賣超金額":"+440","自營買進金額":"64.7","自營賣出金額":"134","自營買賣超金額":"-69.1","合計買進金額":"996","合計賣出金額":"969","合計買賣超金額":"+27.5","法人買賣超註記":"－  ＋  －"},{"排名":"4","代號":"6732","名稱":"昇佳電子","市場":"櫃","成交":"750","漲跌價":"+29","漲跌幅":"+4.02","成交張數":"1183","法人買賣日期":"08\/19","外資買進金額":"163","外資賣出金額":"254","外資買賣超金額":"-91.2","投信買進金額":"341","投信賣出金額":"0","投信買賣超金額":"+341","自營買進金額":"12.2","自營賣出金額":"5.32","自營買賣超金額":"+6.84","合計買進金額":"516","合計賣出金額":"259","合計買賣超金額":"+257","法人買賣超註記":"－  ＋  ＋"},{"排名":"5","代號":"6182","名稱":"合晶","市場":"櫃","成交":"60","漲跌價":"-0.3","漲跌幅":"-0.5","成交張數":"22693","法人買賣日期":"08\/19","外資買進金額":"260","外資賣出金額":"406","外資買賣超金額":"-146","投信買進金額":"330","投信賣出金額":"0","投信買賣超金額":"+330","自營買進金額":"26.8","自營賣出金額":"29.2","自營買賣超金額":"-2.44","合計買進金額":"617","合計賣出金額":"435","合計買賣超金額":"+182","法人買賣超註記":"－  ＋  －"},{"排名":"6","代號":"2351","名稱":"順德","市場":"市","成交":"137","漲跌價":"+1.5","漲跌幅":"+1.11","成交張數":"8245","法人買賣日期":"08\/19","外資買進金額":"261","外資賣出金額":"259","外資買賣超金額":"+1.4","投信買進金額":"269","投信賣出金額":"0","投信買賣超金額":"+269","自營買進金額":"15.7","自營賣出金額":"13.5","自營買賣超金額":"+2.13","合計買進金額":"545","合計賣出金額":"273","合計買賣超金額":"+272","法人買賣超註記":"＋  ＋  ＋"},{"排名":"7","代號":"2330","名稱":"台積電","市場":"市","成交":"559","漲跌價":"-15","漲跌幅":"-2.61","成交張數":"42133","法人買賣日期":"08\/19","外資買進金額":"4066","外資賣出金額":"16471","外資買賣超金額":"-12405","投信買進金額":"264","投信賣出金額":"37.2","投信買賣超金額":"+227","自營買進金額":"321","自營賣出金額":"894","自營買賣超金額":"-572","合計買進金額":"4651","合計賣出金額":"17402","合計買賣超金額":"-12751","法人買賣超註記":"－  ＋  －"},{"排名":"8","代號":"2481","名稱":"強茂","市場":"市","成交":"99","漲跌價":"-1","漲跌幅":"-1","成交張數":"39115","法人買賣日期":"08\/19","外資買進金額":"742","外資賣出金額":"935","外資買賣超金額":"-193","投信買進金額":"193","投信賣出金額":"0","投信買賣超金額":"+193","自營買進金額":"46","自營賣出金額":"21.5","自營買賣超金額":"+24.5","合計買進金額":"981","合計賣出金額":"956","合計買賣超金額":"+24.9","法人買賣超註記":"－  ＋  ＋"},{"排名":"9","代號":"6491","名稱":"晶碩","市場":"市","成交":"516","漲跌價":"+9","漲跌幅":"+1.78","成交張數":"3152","法人買賣日期":"08\/19","外資買進金額":"358","外資賣出金額":"686","外資買賣超金額":"-328","投信買進金額":"182","投信賣出金額":"0","投信買賣超金額":"+182","自營買進金額":"35.1","自營賣出金額":"8.24","自營買賣超金額":"+26.9","合計買進金額":"575","合計賣出金額":"694","合計買賣超金額":"-119","法人買賣超註記":"－  ＋  ＋"},{"排名":"10","代號":"3189","名稱":"景碩","市場":"市","成交":"159","漲跌價":"-12.5","漲跌幅":"-7.29","成交張數":"15249","法人買賣日期":"08\/19","外資買進金額":"751","外資賣出金額":"1116","外資買賣超金額":"-365","投信買進金額":"175","投信賣出金額":"0","投信買賣超金額":"+175","自營買進金額":"80.5","自營賣出金額":"66.5","自營買賣超金額":"+14","合計買進金額":"1007","合計賣出金額":"1182","合計買賣超金額":"-176","法人買賣超註記":"－  ＋  ＋"},{"排名":"11","代號":"3443","名稱":"創意","市場":"市","成交":"383","漲跌價":"-5","漲跌幅":"-1.29","成交張數":"1285","法人買賣日期":"08\/19","外資買進金額":"145","外資賣出金額":"162","外資買賣超金額":"-16.6","投信買進金額":"147","投信賣出金額":"0","投信買賣超金額":"+147","自營買進金額":"9.36","自營賣出金額":"17","自營買賣超金額":"-7.69","合計買進金額":"302","合計賣出金額":"179","合計買賣超金額":"+123","法人買賣超註記":"－  ＋  －"},{"排名":"12","代號":"4919","名稱":"新唐","市場":"市","成交":"135","漲跌價":"-15","漲跌幅":"-10","成交張數":"90925","法人買賣日期":"08\/19","外資買進金額":"1877","外資賣出金額":"1583","外資買賣超金額":"+294","投信買進金額":"143","投信賣出金額":"0","投信買賣超金額":"+143","自營買進金額":"107","自營賣出金額":"191","自營買賣超金額":"-83.5","合計買進金額":"2127","合計賣出金額":"1773","合計買賣超金額":"+354","法人買賣超註記":"＋  ＋  －"},{"排名":"13","代號":"3045","名稱":"台灣大","市場":"市","成交":"103","漲跌價":"-2","漲跌幅":"-1.9","成交張數":"5741","法人買賣日期":"08\/19","外資買進金額":"243","外資賣出金額":"273","外資買賣超金額":"-30.8","投信買進金額":"137","投信賣出金額":"0","投信買賣超金額":"+137","自營買進金額":"14.4","自營賣出金額":"6.42","自營買賣超金額":"+7.97","合計買進金額":"394","合計賣出金額":"280","合計買賣超金額":"+114","法人買賣超註記":"－  ＋  ＋"},{"排名":"14","代號":"5274","名稱":"信驊","市場":"櫃","成交":"2080","漲跌價":"+80","漲跌幅":"+4","成交張數":"383","法人買賣日期":"08\/19","外資買進金額":"428","外資賣出金額":"519","外資買賣超金額":"-90.3","投信買進金額":"153","投信賣出金額":"16.8","投信買賣超金額":"+136","自營買進金額":"19.8","自營賣出金額":"14.7","自營買賣超金額":"+5.08","合計買進金額":"601","合計賣出金額":"550","合計買賣超金額":"+51.3","法人買賣超註記":"－  ＋  ＋"},{"排名":"15","代號":"6683","名稱":"雍智科技","市場":"櫃","成交":"318","漲跌價":"-10","漲跌幅":"-3.05","成交張數":"2580","法人買賣日期":"08\/19","外資買進金額":"139","外資賣出金額":"210","外資買賣超金額":"-71","投信買進金額":"117","投信賣出金額":"0","投信買賣超金額":"+117","自營買進金額":"16.2","自營賣出金額":"4.06","自營買賣超金額":"+12.2","合計買進金額":"272","合計賣出金額":"214","合計買賣超金額":"+58.1","法人買賣超註記":"－  ＋  ＋"},{"排名":"16","代號":"3264","名稱":"欣銓","市場":"櫃","成交":"57.2","漲跌價":"-2.2","漲跌幅":"-3.7","成交張數":"13651","法人買賣日期":"08\/19","外資買進金額":"137","外資賣出金額":"190","外資買賣超金額":"-53","投信買進金額":"114","投信賣出金額":"0","投信買賣超金額":"+114","自營買進金額":"15.2","自營賣出金額":"23.9","自營買賣超金額":"-8.67","合計買進金額":"267","合計賣出金額":"214","合計買賣超金額":"+52.5","法人買賣超註記":"－  ＋  －"},{"排名":"17","代號":"2303","名稱":"聯電","市場":"市","成交":"55.5","漲跌價":"-2.6","漲跌幅":"-4.48","成交張數":"176910","法人買賣日期":"08\/19","外資買進金額":"1455","外資賣出金額":"4343","外資買賣超金額":"-2888","投信買進金額":"118","投信賣出金額":"5.63","投信買賣超金額":"+113","自營買進金額":"194","自營賣出金額":"693","自營買賣超金額":"-499","合計買進金額":"1767","合計賣出金額":"5042","合計買賣超金額":"-3275","法人買賣超註記":"－  ＋  －"},{"排名":"18","代號":"6781","名稱":"AES-KY","市場":"市","成交":"800","漲跌價":"-39","漲跌幅":"-4.65","成交張數":"542","法人買賣日期":"08\/19","外資買進金額":"34.1","外資賣出金額":"73.1","外資買賣超金額":"-39","投信買進金額":"110","投信賣出金額":"0","投信買賣超金額":"+110","自營買進金額":"15","自營賣出金額":"6.64","自營買賣超金額":"+8.31","合計買進金額":"159","合計賣出金額":"79.7","合計買賣超金額":"+79.7","法人買賣超註記":"－  ＋  ＋"},{"排名":"19","代號":"2603","名稱":"長榮","市場":"市","成交":"128","漲跌價":"-8","漲跌幅":"-5.88","成交張數":"321246","法人買賣日期":"08\/19","外資買進金額":"3943","外資賣出金額":"6594","外資買賣超金額":"-2650","投信買進金額":"105","投信賣出金額":"0","投信買賣超金額":"+105","自營買進金額":"809","自營賣出金額":"930","自營買賣超金額":"-121","合計買進金額":"4858","合計賣出金額":"7524","合計買賣超金額":"-2666","法人買賣超註記":"－  ＋  －"},{"排名":"20","代號":"6269","名稱":"台郡","市場":"市","成交":"116","漲跌價":"-2","漲跌幅":"-1.69","成交張數":"2558","法人買賣日期":"08\/19","外資買進金額":"51.4","外資賣出金額":"110","外資買賣超金額":"-58.2","投信買進金額":"104","投信賣出金額":"0","投信買賣超金額":"+104","自營買進金額":"4.81","自營賣出金額":"20.2","自營買賣超金額":"-15.4","合計買進金額":"160","合計賣出金額":"130","合計買賣超金額":"+30.5","法人買賣超註記":"－  ＋  －"},{"排名":"21","代號":"8255","名稱":"朋程","市場":"櫃","成交":"194","漲跌價":"-6.5","漲跌幅":"-3.24","成交張數":"12591","法人買賣日期":"08\/19","外資買進金額":"302","外資賣出金額":"538","外資買賣超金額":"-236","投信買進金額":"102","投信賣出金額":"0","投信買賣超金額":"+102","自營買進金額":"20.4","自營賣出金額":"14.3","自營買賣超金額":"+6.08","合計買進金額":"425","合計賣出金額":"553","合計買賣超金額":"-128","法人買賣超註記":"－  ＋  ＋"},{"排名":"22","代號":"3661","名稱":"世芯-KY","市場":"市","成交":"553","漲跌價":"-23","漲跌幅":"-3.99","成交張數":"2614","法人買賣日期":"08\/19","外資買進金額":"525","外資賣出金額":"405","外資買賣超金額":"+120","投信買進金額":"171","投信賣出金額":"69.5","投信買賣超金額":"+101","自營買進金額":"9.46","自營賣出金額":"23","自營買賣超金額":"-13.5","合計買進金額":"705","合計賣出金額":"497","合計買賣超金額":"+208","法人買賣超註記":"＋  ＋  －"},{"排名":"23","代號":"3533","名稱":"嘉澤","市場":"市","成交":"504","漲跌價":"-3","漲跌幅":"-0.59","成交張數":"631","法人買賣日期":"08\/19","外資買進金額":"56.8","外資賣出金額":"184","外資買賣超金額":"-127","投信買進金額":"100","投信賣出金額":"0.51","投信買賣超金額":"+99.6","自營買進金額":"14.9","自營賣出金額":"3.17","自營買賣超金額":"+11.7","合計買進金額":"172","合計賣出金額":"188","合計買賣超金額":"-16.1","法人買賣超註記":"－  ＋  ＋"},{"排名":"24","代號":"3707","名稱":"漢磊","市場":"櫃","成交":"86","漲跌價":"-3.8","漲跌幅":"-4.23","成交張數":"20949","法人買賣日期":"08\/19","外資買進金額":"526","外資賣出金額":"479","外資買賣超金額":"+46.5","投信買進金額":"125","投信賣出金額":"26.5","投信買賣超金額":"+98.5","自營買進金額":"4.1","自營賣出金額":"13.1","自營買賣超金額":"-8.96","合計買進金額":"655","合計賣出金額":"519","合計買賣超金額":"+136","法人買賣超註記":"＋  ＋  －"},{"排名":"25","代號":"8069","名稱":"元太","市場":"櫃","成交":"73","漲跌價":"-4.1","漲跌幅":"-5.32","成交張數":"11548","法人買賣日期":"08\/19","外資買進金額":"176","外資賣出金額":"277","外資買賣超金額":"-101","投信買進金額":"86.3","投信賣出金額":"0","投信買賣超金額":"+86.3","自營買進金額":"44.8","自營賣出金額":"16.7","自營買賣超金額":"+28.1","合計買進金額":"307","合計賣出金額":"294","合計買賣超金額":"+13.6","法人買賣超註記":"－  ＋  ＋"},{"排名":"26","代號":"2454","名稱":"聯發科","市場":"市","成交":"888","漲跌價":"-24","漲跌幅":"-2.63","成交張數":"5605","法人買賣日期":"08\/19","外資買進金額":"2655","外資賣出金額":"3457","外資買賣超金額":"-802","投信買進金額":"96.5","投信賣出金額":"19.7","投信買賣超金額":"+76.9","自營買進金額":"48.9","自營賣出金額":"182","自營買賣超金額":"-133","合計買進金額":"2800","合計賣出金額":"3658","合計買賣超金額":"-858","法人買賣超註記":"－  ＋  －"},{"排名":"27","代號":"6525","名稱":"捷敏-KY","市場":"市","成交":"99.2","漲跌價":"-6.8","漲跌幅":"-6.42","成交張數":"3804","法人買賣日期":"08\/19","外資買進金額":"70.1","外資賣出金額":"82.6","外資買賣超金額":"-12.5","投信買進金額":"75","投信賣出金額":"0","投信買賣超金額":"+75","自營買進金額":"2.69","自營賣出金額":"0.68","自營買賣超金額":"+2.01","合計買進金額":"148","合計賣出金額":"83.3","合計買賣超金額":"+64.6","法人買賣超註記":"－  ＋  ＋"},{"排名":"28","代號":"8046","名稱":"南電","市場":"市","成交":"360","漲跌價":"-13.5","漲跌幅":"-3.61","成交張數":"5376","法人買賣日期":"08\/19","外資買進金額":"720","外資賣出金額":"768","外資買賣超金額":"-47.7","投信買進金額":"69.5","投信賣出金額":"0","投信買賣超金額":"+69.5","自營買進金額":"48.5","自營賣出金額":"108","自營買賣超金額":"-59.7","合計買進金額":"838","合計賣出金額":"876","合計買賣超金額":"-38","法人買賣超註記":"－  ＋  －"},{"排名":"29","代號":"3532","名稱":"台勝科","市場":"市","成交":"167","漲跌價":"-6","漲跌幅":"-3.47","成交張數":"1263","法人買賣日期":"08\/19","外資買進金額":"82.1","外資賣出金額":"137","外資買賣超金額":"-55","投信買進金額":"66.9","投信賣出金額":"0","投信買賣超金額":"+66.9","自營買進金額":"0","自營賣出金額":"1.35","自營買賣超金額":"-1.35","合計買進金額":"149","合計賣出金額":"138","合計買賣超金額":"+10.5","法人買賣超註記":"－  ＋  －"},{"排名":"30","代號":"2881","名稱":"富邦金","市場":"市","成交":"77","漲跌價":"-1","漲跌幅":"-1.28","成交張數":"23158","法人買賣日期":"08\/19","外資買進金額":"727","外資賣出金額":"933","外資買賣超金額":"-206","投信買進金額":"65.8","投信賣出金額":"1.23","投信買賣超金額":"+64.6","自營買進金額":"24.4","自營賣出金額":"41.5","自營買賣超金額":"-17.1","合計買進金額":"817","合計賣出金額":"976","合計買賣超金額":"-159","法人買賣超註記":"－  ＋  －"},{"排名":"31","代號":"2324","名稱":"仁寶","市場":"市","成交":"22.3","漲跌價":"0","漲跌幅":"0","成交張數":"19146","法人買賣日期":"08\/19","外資買進金額":"194","外資賣出金額":"171","外資買賣超金額":"+23.6","投信買進金額":"63.6","投信賣出金額":"0","投信買賣超金額":"+63.6","自營買進金額":"49.7","自營賣出金額":"5.08","自營買賣超金額":"+44.7","合計買進金額":"307","合計賣出金額":"176","合計買賣超金額":"+132","法人買賣超註記":"＋  ＋  ＋"},{"排名":"32","代號":"2606","名稱":"裕民","市場":"市","成交":"60.4","漲跌價":"-2","漲跌幅":"-3.21","成交張數":"44389","法人買賣日期":"08\/19","外資買進金額":"459","外資賣出金額":"721","外資買賣超金額":"-262","投信買進金額":"52.5","投信賣出金額":"0","投信買賣超金額":"+52.5","自營買進金額":"64.5","自營賣出金額":"57.9","自營買賣超金額":"+6.65","合計買進金額":"576","合計賣出金額":"779","合計買賣超金額":"-203","法人買賣超註記":"－  ＋  ＋"},{"排名":"33","代號":"3529","名稱":"力旺","市場":"櫃","成交":"1235","漲跌價":"+10","漲跌幅":"+0.82","成交張數":"707","法人買賣日期":"08\/19","外資買進金額":"400","外資賣出金額":"495","外資買賣超金額":"-95.7","投信買進金額":"51.8","投信賣出金額":"0","投信買賣超金額":"+51.8","自營買進金額":"16","自營賣出金額":"8.63","自營買賣超金額":"+7.4","合計買進金額":"467","合計賣出金額":"504","合計買賣超金額":"-36.5","法人買賣超註記":"－  ＋  ＋"},{"排名":"34","代號":"2317","名稱":"鴻海","市場":"市","成交":"103","漲跌價":"-4","漲跌幅":"-3.74","成交張數":"52199","法人買賣日期":"08\/19","外資買進金額":"1481","外資賣出金額":"3385","外資買賣超金額":"-1904","投信買進金額":"50.9","投信賣出金額":"0.73","投信買賣超金額":"+50.2","自營買進金額":"60","自營賣出金額":"245","自營買賣超金額":"-185","合計買進金額":"1592","合計賣出金額":"3631","合計買賣超金額":"-2039","法人買賣超註記":"－  ＋  －"},{"排名":"35","代號":"6756","名稱":"威鋒電子","市場":"市","成交":"390","漲跌價":"-21","漲跌幅":"-5.11","成交張數":"1237","法人買賣日期":"08\/19","外資買進金額":"79.4","外資賣出金額":"169","外資買賣超金額":"-89.4","投信買進金額":"48.3","投信賣出金額":"0","投信買賣超金額":"+48.3","自營買進金額":"23.8","自營賣出金額":"31.9","自營買賣超金額":"-8.09","合計買進金額":"151","合計賣出金額":"201","合計買賣超金額":"-49.2","法人買賣超註記":"－  ＋  －"},{"排名":"36","代號":"1909","名稱":"榮成","市場":"市","成交":"27.25","漲跌價":"-0.4","漲跌幅":"-1.45","成交張數":"23978","法人買賣日期":"08\/19","外資買進金額":"195","外資賣出金額":"233","外資買賣超金額":"-37.7","投信買進金額":"47.6","投信賣出金額":"0","投信買賣超金額":"+47.6","自營買進金額":"29.9","自營賣出金額":"20.4","自營買賣超金額":"+9.44","合計買進金額":"273","合計賣出金額":"253","合計買賣超金額":"+19.3","法人買賣超註記":"－  ＋  ＋"},{"排名":"37","代號":"2891","名稱":"中信金","市場":"市","成交":"21.35","漲跌價":"-0.25","漲跌幅":"-1.16","成交張數":"38534","法人買賣日期":"08\/19","外資買進金額":"394","外資賣出金額":"363","外資買賣超金額":"+31.2","投信買進金額":"39.8","投信賣出金額":"0","投信買賣超金額":"+39.8","自營買進金額":"49.2","自營賣出金額":"10.8","自營買賣超金額":"+38.4","合計買進金額":"483","合計賣出金額":"373","合計買賣超金額":"+109","法人買賣超註記":"＋  ＋  ＋"},{"排名":"38","代號":"2409","名稱":"友達","市場":"市","成交":"19.75","漲跌價":"-0.95","漲跌幅":"-4.59","成交張數":"131316","法人買賣日期":"08\/19","外資買進金額":"323","外資賣出金額":"1240","外資買賣超金額":"-917","投信買進金額":"59.8","投信賣出金額":"20","投信買賣超金額":"+39.8","自營買進金額":"95.7","自營賣出金額":"108","自營買賣超金額":"-12.7","合計買進金額":"479","合計賣出金額":"1369","合計買賣超金額":"-890","法人買賣超註記":"－  ＋  －"},{"排名":"39","代號":"2377","名稱":"微星","市場":"市","成交":"123.5","漲跌價":"-2.5","漲跌幅":"-1.98","成交張數":"9488","法人買賣日期":"08\/19","外資買進金額":"559","外資賣出金額":"936","外資買賣超金額":"-378","投信買進金額":"38.2","投信賣出金額":"0","投信買賣超金額":"+38.2","自營買進金額":"55.3","自營賣出金額":"7.47","自營買賣超金額":"+47.9","合計買進金額":"652","合計賣出金額":"944","合計買賣超金額":"-292","法人買賣超註記":"－  ＋  ＋"},{"排名":"40","代號":"2368","名稱":"金像電","市場":"市","成交":"62.1","漲跌價":"-2.1","漲跌幅":"-3.27","成交張數":"13346","法人買賣日期":"08\/19","外資買進金額":"126","外資賣出金額":"411","外資買賣超金額":"-286","投信買進金額":"35","投信賣出金額":"0","投信買賣超金額":"+35","自營買進金額":"24","自營賣出金額":"36.2","自營買賣超金額":"-12.2","合計買進金額":"185","合計賣出金額":"448","合計買賣超金額":"-263","法人買賣超註記":"－  ＋  －"},{"排名":"41","代號":"2412","名稱":"中華電","市場":"市","成交":"116.5","漲跌價":"-1","漲跌幅":"-0.85","成交張數":"9365","法人買賣日期":"08\/19","外資買進金額":"477","外資賣出金額":"546","外資買賣超金額":"-68.8","投信買進金額":"33.4","投信賣出金額":"0","投信買賣超金額":"+33.4","自營買進金額":"2.92","自營賣出金額":"17.7","自營買賣超金額":"-14.8","合計買進金額":"514","合計賣出金額":"564","合計買賣超金額":"-50.2","法人買賣超註記":"－  ＋  －"},{"排名":"42","代號":"2356","名稱":"英業達","市場":"市","成交":"23.8","漲跌價":"+0.05","漲跌幅":"+0.21","成交張數":"11146","法人買賣日期":"08\/19","外資買進金額":"140","外資賣出金額":"85.4","外資買賣超金額":"+54.4","投信買進金額":"33.3","投信賣出金額":"0","投信買賣超金額":"+33.3","自營買進金額":"38.2","自營賣出金額":"2","自營買賣超金額":"+36.2","合計買進金額":"211","合計賣出金額":"87.4","合計買賣超金額":"+124","法人買賣超註記":"＋  ＋  ＋"},{"排名":"43","代號":"2542","名稱":"興富發","市場":"市","成交":"47.55","漲跌價":"-0.85","漲跌幅":"-1.76","成交張數":"4900","法人買賣日期":"08\/19","外資買進金額":"20.2","外資賣出金額":"72.4","外資買賣超金額":"-52.2","投信買進金額":"32.3","投信賣出金額":"0","投信買賣超金額":"+32.3","自營買進金額":"64.2","自營賣出金額":"17.3","自營買賣超金額":"+46.8","合計買進金額":"117","合計賣出金額":"89.8","合計買賣超金額":"+26.9","法人買賣超註記":"－  ＋  ＋"},{"排名":"44","代號":"4938","名稱":"和碩","市場":"市","成交":"64.5","漲跌價":"+0.4","漲跌幅":"+0.62","成交張數":"7900","法人買賣日期":"08\/19","外資買進金額":"267","外資賣出金額":"242","外資買賣超金額":"+24.3","投信買進金額":"32","投信賣出金額":"0","投信買賣超金額":"+32","自營買進金額":"40.6","自營賣出金額":"6.85","自營買賣超金額":"+33.7","合計買進金額":"339","合計賣出金額":"249","合計買賣超金額":"+89.9","法人買賣超註記":"＋  ＋  ＋"},{"排名":"45","代號":"3231","名稱":"緯創","市場":"市","成交":"26.7","漲跌價":"-0.3","漲跌幅":"-1.11","成交張數":"12408","法人買賣日期":"08\/19","外資買進金額":"65.9","外資賣出金額":"248","外資買賣超金額":"-182","投信買進金額":"30.9","投信賣出金額":"0","投信買賣超金額":"+30.9","自營買進金額":"49.3","自營賣出金額":"4.3","自營買賣超金額":"+45","合計買進金額":"146","合計賣出金額":"252","合計買賣超金額":"-106","法人買賣超註記":"－  ＋  ＋"},{"排名":"46","代號":"2385","名稱":"群光","市場":"市","成交":"78.3","漲跌價":"-0.2","漲跌幅":"-0.25","成交張數":"2869","法人買賣日期":"08\/19","外資買進金額":"112","外資賣出金額":"129","外資買賣超金額":"-16.6","投信買進金額":"30.5","投信賣出金額":"0","投信買賣超金額":"+30.5","自營買進金額":"43.9","自營賣出金額":"1.18","自營買賣超金額":"+42.7","合計買進金額":"187","合計賣出金額":"130","合計買賣超金額":"+56.6","法人買賣超註記":"－  ＋  ＋"},{"排名":"47","代號":"2382","名稱":"廣達","市場":"市","成交":"74.9","漲跌價":"-0.3","漲跌幅":"-0.4","成交張數":"6795","法人買賣日期":"08\/19","外資買進金額":"269","外資賣出金額":"404","外資買賣超金額":"-135","投信買進金額":"29.7","投信賣出金額":"0","投信買賣超金額":"+29.7","自營買進金額":"38.5","自營賣出金額":"6.54","自營買賣超金額":"+31.9","合計買進金額":"337","合計賣出金額":"411","合計買賣超金額":"-73.5","法人買賣超註記":"－  ＋  ＋"},{"排名":"48","代號":"2449","名稱":"京元電子","市場":"市","成交":"40.7","漲跌價":"-2.3","漲跌幅":"-5.35","成交張數":"30581","法人買賣日期":"08\/19","外資買進金額":"400","外資賣出金額":"404","外資買賣超金額":"-3.53","投信買進金額":"28.7","投信賣出金額":"0","投信買賣超金額":"+28.7","自營買進金額":"67.9","自營賣出金額":"39.5","自營買賣超金額":"+28.4","合計買進金額":"497","合計賣出金額":"443","合計買賣超金額":"+53.6","法人買賣超註記":"－  ＋  ＋"},{"排名":"49","代號":"4904","名稱":"遠傳","市場":"市","成交":"60.7","漲跌價":"-0.5","漲跌幅":"-0.82","成交張數":"7250","法人買賣日期":"08\/19","外資買進金額":"97","外資賣出金額":"181","外資買賣超金額":"-84.5","投信買進金額":"28.4","投信賣出金額":"0","投信買賣超金額":"+28.4","自營買進金額":"2.9","自營賣出金額":"5","自營買賣超金額":"-2.09","合計買進金額":"128","合計賣出金額":"186","合計買賣超金額":"-58.1","法人買賣超註記":"－  ＋  －"},{"排名":"50","代號":"2108","名稱":"南帝","市場":"市","成交":"109","漲跌價":"-2.5","漲跌幅":"-2.24","成交張數":"2274","法人買賣日期":"08\/19","外資買進金額":"79.4","外資賣出金額":"84.3","外資買賣超金額":"-4.9","投信買進金額":"28.2","投信賣出金額":"0","投信買賣超金額":"+28.2","自營買進金額":"42.9","自營賣出金額":"5.74","自營買賣超金額":"+37.2","合計買進金額":"150","合計賣出金額":"90","合計買賣超金額":"+60.4","法人買賣超註記":"－  ＋  ＋"},{"排名":"51","代號":"2441","名稱":"超豐","市場":"市","成交":"86.8","漲跌價":"-1.7","漲跌幅":"-1.92","成交張數":"2731","法人買賣日期":"08\/19","外資買進金額":"64.7","外資賣出金額":"118","外資買賣超金額":"-53.1","投信買進金額":"28.1","投信賣出金額":"0","投信買賣超金額":"+28.1","自營買進金額":"37.7","自營賣出金額":"5.16","自營買賣超金額":"+32.5","合計買進金額":"130","合計賣出金額":"123","合計買賣超金額":"+7.55","法人買賣超註記":"－  ＋  ＋"},{"排名":"52","代號":"1303","名稱":"南亞","市場":"市","成交":"84","漲跌價":"-2.9","漲跌幅":"-3.34","成交張數":"9030","法人買賣日期":"08\/19","外資買進金額":"264","外資賣出金額":"540","外資買賣超金額":"-276","投信買進金額":"27.6","投信賣出金額":"0","投信買賣超金額":"+27.6","自營買進金額":"16.8","自營賣出金額":"47.9","自營買賣超金額":"-31.1","合計買進金額":"308","合計賣出金額":"587","合計買賣超金額":"-279","法人買賣超註記":"－  ＋  －"},{"排名":"53","代號":"3017","名稱":"奇鋐","市場":"市","成交":"69.8","漲跌價":"-0.9","漲跌幅":"-1.27","成交張數":"5182","法人買賣日期":"08\/19","外資買進金額":"89.9","外資賣出金額":"99.4","外資買賣超金額":"-9.47","投信買進金額":"26.5","投信賣出金額":"0","投信買賣超金額":"+26.5","自營買進金額":"7.85","自營賣出金額":"11.2","自營買賣超金額":"-3.38","合計買進金額":"124","合計賣出金額":"111","合計買賣超金額":"+13.7","法人買賣超註記":"－  ＋  －"},{"排名":"54","代號":"2408","名稱":"南亞科","市場":"市","成交":"65.7","漲跌價":"-3.3","漲跌幅":"-4.78","成交張數":"17524","法人買賣日期":"08\/19","外資買進金額":"309","外資賣出金額":"664","外資買賣超金額":"-355","投信買進金額":"26.3","投信賣出金額":"0","投信買賣超金額":"+26.3","自營買進金額":"19.1","自營賣出金額":"33","自營買賣超金額":"-13.9","合計買進金額":"354","合計賣出金額":"697","合計買賣超金額":"-343","法人買賣超註記":"－  ＋  －"},{"排名":"55","代號":"5269","名稱":"祥碩","市場":"市","成交":"1785","漲跌價":"-45","漲跌幅":"-2.46","成交張數":"490","法人買賣日期":"08\/19","外資買進金額":"288","外資賣出金額":"271","外資買賣超金額":"+17.3","投信買進金額":"25.6","投信賣出金額":"0","投信買賣超金額":"+25.6","自營買進金額":"12.7","自營賣出金額":"23.8","自營買賣超金額":"-11.2","合計買進金額":"326","合計賣出金額":"295","合計買賣超金額":"+31.7","法人買賣超註記":"＋  ＋  －"},{"排名":"56","代號":"2890","名稱":"永豐金","市場":"市","成交":"13.65","漲跌價":"0","漲跌幅":"0","成交張數":"29725","法人買賣日期":"08\/19","外資買進金額":"277","外資賣出金額":"166","外資買賣超金額":"+110","投信買進金額":"25.2","投信賣出金額":"0","投信買賣超金額":"+25.2","自營買進金額":"0.37","自營賣出金額":"2.13","自營買賣超金額":"-1.76","合計買進金額":"302","合計賣出金額":"168","合計買賣超金額":"+134","法人買賣超註記":"＋  ＋  －"},{"排名":"57","代號":"6104","名稱":"創惟","市場":"櫃","成交":"101.5","漲跌價":"-5","漲跌幅":"-4.69","成交張數":"34836","法人買賣日期":"08\/19","外資買進金額":"220","外資賣出金額":"554","外資買賣超金額":"-334","投信買進金額":"62.8","投信賣出金額":"37.7","投信買賣超金額":"+25.1","自營買進金額":"71.4","自營賣出金額":"30","自營買賣超金額":"+41.4","合計買進金額":"355","合計賣出金額":"622","合計買賣超金額":"-267","法人買賣超註記":"－  ＋  ＋"},{"排名":"58","代號":"2357","名稱":"華碩","市場":"市","成交":"311","漲跌價":"-6.5","漲跌幅":"-2.05","成交張數":"3617","法人買賣日期":"08\/19","外資買進金額":"591","外資賣出金額":"658","外資買賣超金額":"-67","投信買進金額":"25","投信賣出金額":"0","投信買賣超金額":"+25","自營買進金額":"45.1","自營賣出金額":"25.7","自營買賣超金額":"+19.3","合計買進金額":"661","合計賣出金額":"684","合計買賣超金額":"-22.6","法人買賣超註記":"－  ＋  ＋"},{"排名":"59","代號":"6415","名稱":"矽力-KY","市場":"市","成交":"3385","漲跌價":"-105","漲跌幅":"-3.01","成交張數":"328","法人買賣日期":"08\/19","外資買進金額":"811","外資賣出金額":"836","外資買賣超金額":"-24.9","投信買進金額":"25","投信賣出金額":"0","投信買賣超金額":"+25","自營買進金額":"65.5","自營賣出金額":"72.3","自營買賣超金額":"-6.79","合計買進金額":"902","合計賣出金額":"909","合計買賣超金額":"-6.63","法人買賣超註記":"－  ＋  －"},{"排名":"60","代號":"2892","名稱":"第一金","市場":"市","成交":"23","漲跌價":"-0.15","漲跌幅":"-0.65","成交張數":"19364","法人買賣日期":"08\/19","外資買進金額":"150","外資賣出金額":"226","外資買賣超金額":"-76","投信買進金額":"24.4","投信賣出金額":"0","投信買賣超金額":"+24.4","自營買進金額":"1.75","自營賣出金額":"5.9","自營買賣超金額":"-4.15","合計買進金額":"176","合計賣出金額":"232","合計買賣超金額":"-55.8","法人買賣超註記":"－  ＋  －"},{"排名":"61","代號":"3035","名稱":"智原","市場":"市","成交":"86.2","漲跌價":"-3.6","漲跌幅":"-4.01","成交張數":"7512","法人買賣日期":"08\/19","外資買進金額":"239","外資賣出金額":"214","外資買賣超金額":"+25.2","投信買進金額":"24.3","投信賣出金額":"0","投信買賣超金額":"+24.3","自營買進金額":"18.7","自營賣出金額":"35.4","自營買賣超金額":"-16.7","合計買進金額":"282","合計賣出金額":"249","合計買賣超金額":"+32.8","法人買賣超註記":"＋  ＋  －"},{"排名":"62","代號":"2882","名稱":"國泰金","市場":"市","成交":"53.8","漲跌價":"-0.6","漲跌幅":"-1.1","成交張數":"35254","法人買賣日期":"08\/19","外資買進金額":"1163","外資賣出金額":"543","外資買賣超金額":"+620","投信買進金額":"23.8","投信賣出金額":"0","投信買賣超金額":"+23.8","自營買進金額":"8.86","自營賣出金額":"46.2","自營買賣超金額":"-37.4","合計買進金額":"1196","合計賣出金額":"590","合計買賣超金額":"+606","法人買賣超註記":"＋  ＋  －"},{"排名":"63","代號":"2912","名稱":"統一超","市場":"市","成交":"286.5","漲跌價":"-2.5","漲跌幅":"-0.87","成交張數":"1676","法人買賣日期":"08\/19","外資買進金額":"389","外資賣出金額":"310","外資買賣超金額":"+79.2","投信買進金額":"23.4","投信賣出金額":"0","投信買賣超金額":"+23.4","自營買進金額":"2.23","自營賣出金額":"7.14","自營買賣超金額":"-4.91","合計買進金額":"414","合計賣出金額":"317","合計買賣超金額":"+97.8","法人買賣超註記":"＋  ＋  －"},{"排名":"64","代號":"2474","名稱":"可成","市場":"市","成交":"175.5","漲跌價":"-2.5","漲跌幅":"-1.4","成交張數":"2257","法人買賣日期":"08\/19","外資買進金額":"114","外資賣出金額":"197","外資買賣超金額":"-83.3","投信買進金額":"23.4","投信賣出金額":"0","投信買賣超金額":"+23.4","自營買進金額":"37.5","自營賣出金額":"14.8","自營買賣超金額":"+22.7","合計買進金額":"175","合計賣出金額":"212","合計買賣超金額":"-37.2","法人買賣超註記":"－  ＋  ＋"},{"排名":"65","代號":"3714","名稱":"富采","市場":"市","成交":"74.9","漲跌價":"-6.3","漲跌幅":"-7.76","成交張數":"23141","法人買賣日期":"08\/19","外資買進金額":"256","外資賣出金額":"461","外資買賣超金額":"-205","投信買進金額":"23.2","投信賣出金額":"0","投信買賣超金額":"+23.2","自營買進金額":"22.1","自營賣出金額":"13.6","自營買賣超金額":"+8.43","合計買進金額":"302","合計賣出金額":"475","合計買賣超金額":"-174","法人買賣超註記":"－  ＋  ＋"},{"排名":"66","代號":"4966","名稱":"譜瑞-KY","市場":"櫃","成交":"1600","漲跌價":"-60","漲跌幅":"-3.61","成交張數":"492","法人買賣日期":"08\/19","外資買進金額":"419","外資賣出金額":"549","外資買賣超金額":"-130","投信買進金額":"22.6","投信賣出金額":"0","投信買賣超金額":"+22.6","自營買進金額":"3.22","自營賣出金額":"13.5","自營買賣超金額":"-10.3","合計買進金額":"445","合計賣出金額":"563","合計買賣超金額":"-118","法人買賣超註記":"－  ＋  －"},{"排名":"67","代號":"1216","名稱":"統一","市場":"市","成交":"69.1","漲跌價":"-1","漲跌幅":"-1.43","成交張數":"13470","法人買賣日期":"08\/19","外資買進金額":"172","外資賣出金額":"742","外資買賣超金額":"-571","投信買進金額":"22.5","投信賣出金額":"0","投信買賣超金額":"+22.5","自營買進金額":"19.9","自營賣出金額":"14.3","自營買賣超金額":"+5.64","合計買進金額":"214","合計賣出金額":"756","合計買賣超金額":"-542","法人買賣超註記":"－  ＋  ＋"},{"排名":"68","代號":"2354","名稱":"鴻準","市場":"市","成交":"64.5","漲跌價":"-2.3","漲跌幅":"-3.44","成交張數":"14114","法人買賣日期":"08\/19","外資買進金額":"304","外資賣出金額":"351","外資買賣超金額":"-46.9","投信買進金額":"22.4","投信賣出金額":"0","投信買賣超金額":"+22.4","自營買進金額":"22","自營賣出金額":"11.5","自營買賣超金額":"+10.4","合計買進金額":"349","合計賣出金額":"363","合計買賣超金額":"-14.1","法人買賣超註記":"－  ＋  ＋"},{"排名":"69","代號":"1402","名稱":"遠東新","市場":"市","成交":"28.3","漲跌價":"-0.55","漲跌幅":"-1.91","成交張數":"8983","法人買賣日期":"08\/19","外資買進金額":"128","外資賣出金額":"205","外資買賣超金額":"-76.9","投信買進金額":"22.3","投信賣出金額":"0","投信買賣超金額":"+22.3","自營買進金額":"1.02","自營賣出金額":"3.73","自營買賣超金額":"-2.7","合計買進金額":"152","合計賣出金額":"209","合計買賣超金額":"-57.2","法人買賣超註記":"－  ＋  －"},{"排名":"70","代號":"2809","名稱":"京城銀","市場":"市","成交":"42.95","漲跌價":"+0.1","漲跌幅":"+0.23","成交張數":"4035","法人買賣日期":"08\/19","外資買進金額":"97.2","外資賣出金額":"25.2","外資買賣超金額":"+71.9","投信買進金額":"22.2","投信賣出金額":"0","投信買賣超金額":"+22.2","自營買進金額":"32","自營賣出金額":"1.94","自營買賣超金額":"+30.1","合計買進金額":"151","合計賣出金額":"27.2","合計買賣超金額":"+124","法人買賣超註記":"＋  ＋  ＋"},{"排名":"71","代號":"5522","名稱":"遠雄","市場":"市","成交":"57.6","漲跌價":"+0.1","漲跌幅":"+0.17","成交張數":"1353","法人買賣日期":"08\/19","外資買進金額":"17.7","外資賣出金額":"32.1","外資買賣超金額":"-14.4","投信買進金額":"21.7","投信賣出金額":"0","投信買賣超金額":"+21.7","自營買進金額":"31.1","自營賣出金額":"1.04","自營買賣超金額":"+30.1","合計買進金額":"70.5","合計賣出金額":"33.2","合計買賣超金額":"+37.3","法人買賣超註記":"－  ＋  ＋"},{"排名":"72","代號":"2308","名稱":"台達電","市場":"市","成交":"269","漲跌價":"+2","漲跌幅":"+0.75","成交張數":"10481","法人買賣日期":"08\/19","外資買進金額":"2322","外資賣出金額":"1811","外資買賣超金額":"+511","投信買進金額":"20.3","投信賣出金額":"0","投信買賣超金額":"+20.3","自營買進金額":"15.4","自營賣出金額":"43.8","自營買賣超金額":"-28.4","合計買進金額":"2357","合計賣出金額":"1855","合計買賣超金額":"+502","法人買賣超註記":"＋  ＋  －"},{"排名":"73","代號":"2379","名稱":"瑞昱","市場":"市","成交":"517","漲跌價":"-34","漲跌幅":"-6.17","成交張數":"3064","法人買賣日期":"08\/19","外資買進金額":"550","外資賣出金額":"939","外資買賣超金額":"-390","投信買進金額":"20","投信賣出金額":"0","投信買賣超金額":"+20","自營買進金額":"26.8","自營賣出金額":"26","自營買賣超金額":"+0.8","合計買進金額":"597","合計賣出金額":"965","合計買賣超金額":"-369","法人買賣超註記":"－  ＋  ＋"},{"排名":"74","代號":"3526","名稱":"凡甲","市場":"櫃","成交":"161.5","漲跌價":"-9","漲跌幅":"-5.28","成交張數":"2318","法人買賣日期":"08\/19","外資買進金額":"24.8","外資賣出金額":"127","外資買賣超金額":"-102","投信買進金額":"19.8","投信賣出金額":"0","投信買賣超金額":"+19.8","自營買進金額":"1.65","自營賣出金額":"3.04","自營買賣超金額":"-1.39","合計買進金額":"46.2","合計賣出金額":"130","合計買賣超金額":"-83.6","法人買賣超註記":"－  ＋  －"},{"排名":"75","代號":"8299","名稱":"群聯","市場":"櫃","成交":"418.5","漲跌價":"-24.5","漲跌幅":"-5.53","成交張數":"2555","法人買賣日期":"08\/19","外資買進金額":"206","外資賣出金額":"298","外資買賣超金額":"-92.8","投信買進金額":"19.6","投信賣出金額":"0","投信買賣超金額":"+19.6","自營買進金額":"13.6","自營賣出金額":"41.4","自營買賣超金額":"-27.8","合計買進金額":"239","合計賣出金額":"340","合計買賣超金額":"-101","法人買賣超註記":"－  ＋  －"},{"排名":"76","代號":"3653","名稱":"健策","市場":"市","成交":"293.5","漲跌價":"-3","漲跌幅":"-1.01","成交張數":"722","法人買賣日期":"08\/19","外資買進金額":"38.2","外資賣出金額":"60.6","外資買賣超金額":"-22.5","投信買進金額":"18.9","投信賣出金額":"0","投信買賣超金額":"+18.9","自營買進金額":"9.26","自營賣出金額":"12.6","自營買賣超金額":"-3.33","合計買進金額":"66.4","合計賣出金額":"73.2","合計買賣超金額":"-6.88","法人買賣超註記":"－  ＋  －"},{"排名":"77","代號":"5347","名稱":"世界","市場":"櫃","成交":"136","漲跌價":"-1","漲跌幅":"-0.73","成交張數":"8854","法人買賣日期":"08\/19","外資買進金額":"737","外資賣出金額":"532","外資買賣超金額":"+205","投信買進金額":"36.2","投信賣出金額":"17.3","投信買賣超金額":"+18.8","自營買進金額":"14.6","自營賣出金額":"42.8","自營買賣超金額":"-28.1","合計買進金額":"787","合計賣出金額":"592","合計買賣超金額":"+195","法人買賣超註記":"＋  ＋  －"},{"排名":"78","代號":"2404","名稱":"漢唐","市場":"市","成交":"186","漲跌價":"-6.5","漲跌幅":"-3.38","成交張數":"797","法人買賣日期":"08\/19","外資買進金額":"19.4","外資賣出金額":"61.9","外資買賣超金額":"-42.6","投信買進金額":"18.8","投信賣出金額":"0","投信買賣超金額":"+18.8","自營買進金額":"27.6","自營賣出金額":"1.73","自營買賣超金額":"+25.9","合計買進金額":"65.8","合計賣出金額":"63.7","合計買賣超金額":"+2.12","法人買賣超註記":"－  ＋  ＋"},{"排名":"79","代號":"6411","名稱":"晶焱","市場":"櫃","成交":"138.5","漲跌價":"-7","漲跌幅":"-4.81","成交張數":"6140","法人買賣日期":"08\/19","外資買進金額":"214","外資賣出金額":"278","外資買賣超金額":"-63.4","投信買進金額":"16.9","投信賣出金額":"0","投信買賣超金額":"+16.9","自營買進金額":"9.62","自營賣出金額":"24","自營買賣超金額":"-14.4","合計買進金額":"241","合計賣出金額":"302","合計買賣超金額":"-60.9","法人買賣超註記":"－  ＋  －"},{"排名":"80","代號":"3587","名稱":"閎康","市場":"櫃","成交":"141","漲跌價":"+2","漲跌幅":"+1.44","成交張數":"2508","法人買賣日期":"08\/19","外資買進金額":"38.5","外資賣出金額":"97.7","外資買賣超金額":"-59.2","投信買進金額":"14","投信賣出金額":"0","投信買賣超金額":"+14","自營買進金額":"4.08","自營賣出金額":"5.01","自營買賣超金額":"-0.93","合計買進金額":"56.6","合計賣出金額":"103","合計買賣超金額":"-46.2","法人買賣超註記":"－  ＋  －"},{"排名":"81","代號":"3711","名稱":"日月光投控","市場":"市","成交":"115.5","漲跌價":"-3.5","漲跌幅":"-2.94","成交張數":"15451","法人買賣日期":"08\/19","外資買進金額":"1076","外資賣出金額":"1311","外資買賣超金額":"-235","投信買進金額":"13.1","投信賣出金額":"0","投信買賣超金額":"+13.1","自營買進金額":"30.5","自營賣出金額":"48.5","自營買賣超金額":"-18","合計買進金額":"1120","合計賣出金額":"1360","合計買賣超金額":"-240","法人買賣超註記":"－  ＋  －"},{"排名":"82","代號":"8215","名稱":"明基材","市場":"市","成交":"37.55","漲跌價":"+0.55","漲跌幅":"+1.49","成交張數":"56823","法人買賣日期":"08\/19","外資買進金額":"253","外資賣出金額":"468","外資買賣超金額":"-216","投信買進金額":"13.1","投信賣出金額":"0","投信買賣超金額":"+13.1","自營買進金額":"16.7","自營賣出金額":"4.64","自營買賣超金額":"+12.1","合計買進金額":"282","合計賣出金額":"473","合計買賣超金額":"-191","法人買賣超註記":"－  ＋  ＋"},{"排名":"83","代號":"3034","名稱":"聯詠","市場":"市","成交":"470.5","漲跌價":"-21","漲跌幅":"-4.27","成交張數":"9082","法人買賣日期":"08\/19","外資買進金額":"2083","外資賣出金額":"2014","外資買賣超金額":"+69.4","投信買進金額":"17.8","投信賣出金額":"5.3","投信買賣超金額":"+12.5","自營買進金額":"83.8","自營賣出金額":"377","自營買賣超金額":"-293","合計買進金額":"2185","合計賣出金額":"2396","合計買賣超金額":"-211","法人買賣超註記":"＋  ＋  －"},{"排名":"84","代號":"3551","名稱":"世禾","市場":"櫃","成交":"61.4","漲跌價":"-2.6","漲跌幅":"-4.06","成交張數":"6381","法人買賣日期":"08\/19","外資買進金額":"30.6","外資賣出金額":"49.4","外資買賣超金額":"-18.8","投信買進金額":"12.4","投信賣出金額":"0","投信買賣超金額":"+12.4","自營買進金額":"9.67","自營賣出金額":"0.71","自營買賣超金額":"+8.95","合計買進金額":"52.6","合計賣出金額":"50.1","合計買賣超金額":"+2.53","法人買賣超註記":"－  ＋  ＋"},{"排名":"85","代號":"1565","名稱":"精華","市場":"櫃","成交":"336","漲跌價":"-22","漲跌幅":"-6.15","成交張數":"925","法人買賣日期":"08\/19","外資買進金額":"57","外資賣出金額":"126","外資買賣超金額":"-69.3","投信買進金額":"12","投信賣出金額":"0","投信買賣超金額":"+12","自營買進金額":"2.39","自營賣出金額":"14.2","自營買賣超金額":"-11.8","合計買進金額":"71.4","合計賣出金額":"141","合計買賣超金額":"-69.2","法人買賣超註記":"－  ＋  －"},{"排名":"86","代號":"3008","名稱":"大立光","市場":"市","成交":"2740","漲跌價":"-45","漲跌幅":"-1.62","成交張數":"461","法人買賣日期":"08\/19","外資買進金額":"824","外資賣出金額":"679","外資買賣超金額":"+145","投信買進金額":"11.7","投信賣出金額":"0","投信買賣超金額":"+11.7","自營買進金額":"5.96","自營賣出金額":"44.1","自營買賣超金額":"-38.1","合計買進金額":"842","合計賣出金額":"723","合計買賣超金額":"+119","法人買賣超註記":"＋  ＋  －"},{"排名":"87","代號":"2345","名稱":"智邦","市場":"市","成交":"289","漲跌價":"+3","漲跌幅":"+1.05","成交張數":"4772","法人買賣日期":"08\/19","外資買進金額":"1150","外資賣出金額":"1093","外資買賣超金額":"+56.7","投信買進金額":"11.9","投信賣出金額":"0.28","投信買賣超金額":"+11.7","自營買進金額":"17.1","自營賣出金額":"17.6","自營買賣超金額":"-0.56","合計買進金額":"1179","合計賣出金額":"1111","合計買賣超金額":"+67.8","法人買賣超註記":"＋  ＋  －"},{"排名":"88","代號":"6202","名稱":"盛群","市場":"市","成交":"117","漲跌價":"-4.5","漲跌幅":"-3.7","成交張數":"4260","法人買賣日期":"08\/19","外資買進金額":"126","外資賣出金額":"152","外資買賣超金額":"-26.2","投信買進金額":"11.5","投信賣出金額":"0","投信買賣超金額":"+11.5","自營買進金額":"10.2","自營賣出金額":"10.8","自營買賣超金額":"-0.62","合計買進金額":"148","合計賣出金額":"163","合計買賣超金額":"-15.3","法人買賣超註記":"－  ＋  －"},{"排名":"89","代號":"2883","名稱":"開發金","市場":"市","成交":"13.2","漲跌價":"-0.4","漲跌幅":"-2.94","成交張數":"118991","法人買賣日期":"08\/19","外資買進金額":"353","外資賣出金額":"392","外資買賣超金額":"-39.4","投信買進金額":"26","投信賣出金額":"15.1","投信買賣超金額":"+10.9","自營買進金額":"42.8","自營賣出金額":"72.6","自營買賣超金額":"-29.8","合計買進金額":"422","合計賣出金額":"480","合計買賣超金額":"-58.2","法人買賣超註記":"－  ＋  －"},{"排名":"90","代號":"8081","名稱":"致新","市場":"市","成交":"257.5","漲跌價":"-11.5","漲跌幅":"-4.28","成交張數":"1263","法人買賣日期":"08\/19","外資買進金額":"108","外資賣出金額":"84.7","外資買賣超金額":"+23.2","投信買進金額":"18.6","投信賣出金額":"7.99","投信買賣超金額":"+10.7","自營買進金額":"6.39","自營賣出金額":"4.79","自營買賣超金額":"+1.6","合計買進金額":"133","合計賣出金額":"97.4","合計買賣超金額":"+35.4","法人買賣超註記":"＋  ＋  ＋"},{"排名":"91","代號":"2886","名稱":"兆豐金","市場":"市","成交":"31.3","漲跌價":"-0.15","漲跌幅":"-0.48","成交張數":"21901","法人買賣日期":"08\/19","外資買進金額":"340","外資賣出金額":"331","外資買賣超金額":"+8.84","投信買進金額":"27.4","投信賣出金額":"16.9","投信買賣超金額":"+10.5","自營買進金額":"34.6","自營賣出金額":"10.3","自營買賣超金額":"+24.3","合計買進金額":"402","合計賣出金額":"358","合計買賣超金額":"+43.7","法人買賣超註記":"＋  ＋  ＋"},{"排名":"92","代號":"9921","名稱":"巨大","市場":"市","成交":"307.5","漲跌價":"-13","漲跌幅":"-4.06","成交張數":"997","法人買賣日期":"08\/19","外資買進金額":"125","外資賣出金額":"242","外資買賣超金額":"-117","投信買進金額":"10.5","投信賣出金額":"0","投信買賣超金額":"+10.5","自營買進金額":"0.92","自營賣出金額":"12.5","自營買賣超金額":"-11.5","合計買進金額":"136","合計賣出金額":"255","合計買賣超金額":"-118","法人買賣超註記":"－  ＋  －"},{"排名":"93","代號":"0056","名稱":"元大高股息","市場":"市","成交":"32.32","漲跌價":"-0.75","漲跌幅":"-2.27","成交張數":"45729","法人買賣日期":"08\/19","外資買進金額":"36.1","外資賣出金額":"81.6","外資買賣超金額":"-45.5","投信買進金額":"9.75","投信賣出金額":"0","投信買賣超金額":"+9.75","自營買進金額":"10.1","自營賣出金額":"1212","自營買賣超金額":"-1202","合計買進金額":"56","合計賣出金額":"1294","合計買賣超金額":"-1238","法人買賣超註記":"－  ＋  －"},{"排名":"94","代號":"0050","名稱":"元大台灣50","市場":"市","成交":"131.8","漲跌價":"-3.1","漲跌幅":"-2.3","成交張數":"28091","法人買賣日期":"08\/19","外資買進金額":"133","外資賣出金額":"2492","外資買賣超金額":"-2359","投信買進金額":"8.87","投信賣出金額":"0","投信買賣超金額":"+8.87","自營買進金額":"309","自營賣出金額":"719","自營買賣超金額":"-410","合計買進金額":"452","合計賣出金額":"3212","合計買賣超金額":"-2760","法人買賣超註記":"－  ＋  －"},{"排名":"95","代號":"2338","名稱":"光罩","市場":"市","成交":"73","漲跌價":"-3.2","漲跌幅":"-4.2","成交張數":"10692","法人買賣日期":"08\/19","外資買進金額":"166","外資賣出金額":"254","外資買賣超金額":"-87.7","投信買進金額":"8.84","投信賣出金額":"0","投信買賣超金額":"+8.84","自營買進金額":"18.5","自營賣出金額":"39.3","自營買賣超金額":"-20.8","合計買進金額":"193","合計賣出金額":"293","合計買賣超金額":"-99.7","法人買賣超註記":"－  ＋  －"},{"排名":"96","代號":"3037","名稱":"欣興","市場":"市","成交":"131","漲跌價":"-7","漲跌幅":"-5.07","成交張數":"18095","法人買賣日期":"08\/19","外資買進金額":"639","外資賣出金額":"1088","外資買賣超金額":"-450","投信買進金額":"10.3","投信賣出金額":"1.47","投信買賣超金額":"+8.8","自營買進金額":"56.3","自營賣出金額":"67.5","自營買賣超金額":"-11.2","合計買進金額":"705","合計賣出金額":"1157","合計買賣超金額":"-452","法人買賣超註記":"－  ＋  －"},{"排名":"97","代號":"3044","名稱":"健鼎","市場":"市","成交":"110","漲跌價":"-2","漲跌幅":"-1.79","成交張數":"1529","法人買賣日期":"08\/19","外資買進金額":"21.9","外資賣出金額":"59.3","外資買賣超金額":"-37.4","投信買進金額":"8.18","投信賣出金額":"0","投信買賣超金額":"+8.18","自營買進金額":"36.6","自營賣出金額":"4.23","自營買賣超金額":"+32.4","合計買進金額":"66.7","合計賣出金額":"63.5","合計買賣超金額":"+3.13","法人買賣超註記":"－  ＋  ＋"},{"排名":"98","代號":"3675","名稱":"德微","市場":"櫃","成交":"148","漲跌價":"+3","漲跌幅":"+2.07","成交張數":"5175","法人買賣日期":"08\/19","外資買進金額":"169","外資賣出金額":"139","外資買賣超金額":"+30.2","投信買進金額":"7.93","投信賣出金額":"0","投信買賣超金額":"+7.93","自營買進金額":"16","自營賣出金額":"11","自營買賣超金額":"+5.03","合計買進金額":"193","合計賣出金額":"150","合計買賣超金額":"+43.1","法人買賣超註記":"＋  ＋  ＋"},{"排名":"99","代號":"8016","名稱":"矽創","市場":"市","成交":"314.5","漲跌價":"-20.5","漲跌幅":"-6.12","成交張數":"6016","法人買賣日期":"08\/19","外資買進金額":"539","外資賣出金額":"501","外資買賣超金額":"+38.2","投信買進金額":"7.84","投信賣出金額":"0","投信買賣超金額":"+7.84","自營買進金額":"38.2","自營賣出金額":"72.2","自營買賣超金額":"-34","合計買進金額":"585","合計賣出金額":"573","合計買賣超金額":"+12.1","法人買賣超註記":"＋  ＋  －"},{"排名":"100","代號":"3105","名稱":"穩懋","市場":"櫃","成交":"324.5","漲跌價":"-3.5","漲跌幅":"-1.07","成交張數":"3169","法人買賣日期":"08\/19","外資買進金額":"614","外資賣出金額":"675","外資買賣超金額":"-61.7","投信買進金額":"9.76","投信賣出金額":"3.9","投信買賣超金額":"+5.86","自營買進金額":"17.9","自營賣出金額":"31","自營買賣超金額":"-13.1","合計買進金額":"641","合計賣出金額":"710","合計買賣超金額":"-68.9","法人買賣超註記":"－  ＋  －"},{"排名":"101","代號":"6669","名稱":"緯穎","市場":"市","成交":"889","漲跌價":"+23","漲跌幅":"+2.66","成交張數":"983","法人買賣日期":"08\/19","外資買進金額":"696","外資賣出金額":"617","外資買賣超金額":"+78.4","投信買進金額":"5.26","投信賣出金額":"0","投信買賣超金額":"+5.26","自營買進金額":"17.4","自營賣出金額":"17.9","自營買賣超金額":"-0.51","合計買進金額":"719","合計賣出金額":"635","合計買賣超金額":"+83.2","法人買賣超註記":"＋  ＋  －"},{"排名":"102","代號":"5871","名稱":"中租-KY","市場":"市","成交":"225.5","漲跌價":"-5.5","漲跌幅":"-2.38","成交張數":"4061","法人買賣日期":"08\/19","外資買進金額":"655","外資賣出金額":"569","外資買賣超金額":"+86.7","投信買進金額":"5.21","投信賣出金額":"0","投信買賣超金額":"+5.21","自營買進金額":"3.62","自營賣出金額":"19.5","自營買賣超金額":"-15.9","合計買進金額":"664","合計賣出金額":"588","合計買賣超金額":"+76.1","法人買賣超註記":"＋  ＋  －"},{"排名":"103","代號":"2609","名稱":"陽明","市場":"市","成交":"126.5","漲跌價":"-10","漲跌幅":"-7.33","成交張數":"348451","法人買賣日期":"08\/19","外資買進金額":"2175","外資賣出金額":"3973","外資買賣超金額":"-1799","投信買進金額":"5.16","投信賣出金額":"0","投信買賣超金額":"+5.16","自營買進金額":"158","自營賣出金額":"341","自營買賣超金額":"-183","合計買進金額":"2338","合計賣出金額":"4314","合計買賣超金額":"-1976","法人買賣超註記":"－  ＋  －"},{"排名":"104","代號":"2615","名稱":"萬海","市場":"市","成交":"213","漲跌價":"-13","漲跌幅":"-5.75","成交張數":"172898","法人買賣日期":"08\/19","外資買進金額":"3124","外資賣出金額":"5410","外資買賣超金額":"-2286","投信買進金額":"4.24","投信賣出金額":"0","投信買賣超金額":"+4.24","自營買進金額":"301","自營賣出金額":"316","自營買賣超金額":"-15.1","合計買進金額":"3430","合計賣出金額":"5727","合計買賣超金額":"-2297","法人買賣超註記":"－  ＋  －"},{"排名":"105","代號":"2344","名稱":"華邦電","市場":"市","成交":"28.9","漲跌價":"-1.2","漲跌幅":"-3.99","成交張數":"48547","法人買賣日期":"08\/19","外資買進金額":"431","外資賣出金額":"531","外資買賣超金額":"-100","投信買進金額":"4.17","投信賣出金額":"0","投信買賣超金額":"+4.17","自營買進金額":"28.6","自營賣出金額":"68.7","自營買賣超金額":"-40.1","合計買進金額":"463","合計賣出金額":"599","合計買賣超金額":"-136","法人買賣超註記":"－  ＋  －"},{"排名":"106","代號":"1301","名稱":"台塑","市場":"市","成交":"96.7","漲跌價":"-2.8","漲跌幅":"-2.81","成交張數":"8149","法人買賣日期":"08\/19","外資買進金額":"244","外資賣出金額":"602","外資買賣超金額":"-359","投信買進金額":"4.79","投信賣出金額":"0.68","投信買賣超金額":"+4.1","自營買進金額":"6.64","自營賣出金額":"33.3","自營買賣超金額":"-26.6","合計買進金額":"255","合計賣出金額":"636","合計買賣超金額":"-381","法人買賣超註記":"－  ＋  －"},{"排名":"107","代號":"2360","名稱":"致茂","市場":"市","成交":"177.5","漲跌價":"-4","漲跌幅":"-2.2","成交張數":"401","法人買賣日期":"08\/19","外資買進金額":"30.6","外資賣出金額":"57.8","外資買賣超金額":"-27.2","投信買進金額":"3.37","投信賣出金額":"0","投信買賣超金額":"+3.37","自營買進金額":"0.18","自營賣出金額":"3.39","自營買賣超金額":"-3.21","合計買進金額":"34.1","合計賣出金額":"61.2","合計買賣超金額":"-27.1","法人買賣超註記":"－  ＋  －"},{"排名":"108","代號":"5285","名稱":"界霖","市場":"市","成交":"102","漲跌價":"-5.5","漲跌幅":"-5.12","成交張數":"6326","法人買賣日期":"08\/19","外資買進金額":"153","外資賣出金額":"112","外資買賣超金額":"+40.8","投信買進金額":"3.09","投信賣出金額":"0","投信買賣超金額":"+3.09","自營買進金額":"3.09","自營賣出金額":"4.53","自營買賣超金額":"-1.44","合計買進金額":"159","合計賣出金額":"117","合計買賣超金額":"+42.4","法人買賣超註記":"＋  ＋  －"},{"排名":"109","代號":"1326","名稱":"台化","市場":"市","成交":"80.2","漲跌價":"-1.5","漲跌幅":"-1.84","成交張數":"5913","法人買賣日期":"08\/19","外資買進金額":"173","外資賣出金額":"392","外資買賣超金額":"-218","投信買進金額":"3.05","投信賣出金額":"0","投信買賣超金額":"+3.05","自營買進金額":"2.57","自營賣出金額":"12.1","自營買賣超金額":"-9.51","合計買進金額":"179","合計賣出金額":"404","合計買賣超金額":"-225","法人買賣超註記":"－  ＋  －"},{"排名":"110","代號":"5009","名稱":"榮剛","市場":"櫃","成交":"24.2","漲跌價":"-1.4","漲跌幅":"-5.47","成交張數":"13814","法人買賣日期":"08\/19","外資買進金額":"69","外資賣出金額":"79.9","外資買賣超金額":"-10.9","投信買進金額":"3.04","投信賣出金額":"0","投信買賣超金額":"+3.04","自營買進金額":"0.48","自營賣出金額":"7.51","自營買賣超金額":"-7.03","合計買進金額":"72.5","合計賣出金額":"87.4","合計買賣超金額":"-14.9","法人買賣超註記":"－  ＋  －"},{"排名":"111","代號":"2337","名稱":"旺宏","市場":"市","成交":"38.2","漲跌價":"-1.5","漲跌幅":"-3.78","成交張數":"27381","法人買賣日期":"08\/19","外資買進金額":"222","外資賣出金額":"409","外資買賣超金額":"-187","投信買進金額":"2.81","投信賣出金額":"0","投信買賣超金額":"+2.81","自營買進金額":"9.8","自營賣出金額":"35.4","自營買賣超金額":"-25.6","合計買進金額":"235","合計賣出金額":"444","合計買賣超金額":"-210","法人買賣超註記":"－  ＋  －"},{"排名":"112","代號":"2884","名稱":"玉山金","市場":"市","成交":"26.95","漲跌價":"-0.05","漲跌幅":"-0.19","成交張數":"36163","法人買賣日期":"08\/19","外資買進金額":"606","外資賣出金額":"453","外資買賣超金額":"+153","投信買進金額":"2.56","投信賣出金額":"0","投信買賣超金額":"+2.56","自營買進金額":"55.9","自營賣出金額":"60.4","自營買賣超金額":"-4.52","合計買進金額":"664","合計賣出金額":"514","合計買賣超金額":"+151","法人買賣超註記":"＋  ＋  －"},{"排名":"113","代號":"2458","名稱":"義隆","市場":"市","成交":"152.5","漲跌價":"-5.5","漲跌幅":"-3.48","成交張數":"2683","法人買賣日期":"08\/19","外資買進金額":"82","外資賣出金額":"208","外資買賣超金額":"-126","投信買進金額":"2.3","投信賣出金額":"0","投信買賣超金額":"+2.3","自營買進金額":"37.9","自營賣出金額":"11.4","自營買賣超金額":"+26.5","合計買進金額":"122","合計賣出金額":"219","合計買賣超金額":"-97","法人買賣超註記":"－  ＋  ＋"},{"排名":"114","代號":"5288","名稱":"豐祥-KY","市場":"市","成交":"142","漲跌價":"-1.5","漲跌幅":"-1.05","成交張數":"103","法人買賣日期":"08\/19","外資買進金額":"4.55","外資賣出金額":"1.99","外資買賣超金額":"+2.56","投信買進金額":"2.13","投信賣出金額":"0","投信買賣超金額":"+2.13","自營買進金額":"0","自營賣出金額":"0","自營買賣超金額":"0","合計買進金額":"6.69","合計賣出金額":"1.99","合計買賣超金額":"+4.69","法人買賣超註記":"＋  ＋  ・"},{"排名":"115","代號":"2352","名稱":"佳世達","市場":"市","成交":"28.6","漲跌價":"-0.65","漲跌幅":"-2.22","成交張數":"6178","法人買賣日期":"08\/19","外資買進金額":"12.4","外資賣出金額":"77.2","外資買賣超金額":"-64.7","投信買進金額":"1.98","投信賣出金額":"0","投信買賣超金額":"+1.98","自營買進金額":"3.79","自營賣出金額":"8.9","自營買賣超金額":"-5.11","合計買進金額":"18.2","合計賣出金額":"86.1","合計買賣超金額":"-67.9","法人買賣超註記":"－  ＋  －"},{"排名":"116","代號":"6672","名稱":"騰輝電子-KY","市場":"市","成交":"151.5","漲跌價":"-8","漲跌幅":"-5.02","成交張數":"1765","法人買賣日期":"08\/19","外資買進金額":"60","外資賣出金額":"118","外資買賣超金額":"-58.2","投信買進金額":"1.88","投信賣出金額":"0","投信買賣超金額":"+1.88","自營買進金額":"0","自營賣出金額":"0.2","自營買賣超金額":"-0.19","合計買進金額":"61.9","合計賣出金額":"118","合計買賣超金額":"-56.5","法人買賣超註記":"－  ＋  －"},{"排名":"117","代號":"2395","名稱":"研華","市場":"市","成交":"362","漲跌價":"-2.5","漲跌幅":"-0.69","成交張數":"829","法人買賣日期":"08\/19","外資買進金額":"256","外資賣出金額":"241","外資買賣超金額":"+15.1","投信買進金額":"1.81","投信賣出金額":"0","投信買賣超金額":"+1.81","自營買進金額":"1.46","自營賣出金額":"4.37","自營買賣超金額":"-2.91","合計買進金額":"259","合計賣出金額":"245","合計買賣超金額":"+14","法人買賣超註記":"＋  ＋  －"},{"排名":"118","代號":"1590","名稱":"亞德客-KY","市場":"市","成交":"867","漲跌價":"-16","漲跌幅":"-1.81","成交張數":"771","法人買賣日期":"08\/19","外資買進金額":"496","外資賣出金額":"445","外資買賣超金額":"+51","投信買進金額":"1.74","投信賣出金額":"0","投信買賣超金額":"+1.74","自營買進金額":"13.9","自營賣出金額":"26.3","自營買賣超金額":"-12.4","合計買進金額":"512","合計賣出金額":"472","合計買賣超金額":"+40.4","法人買賣超註記":"＋  ＋  －"},{"排名":"119","代號":"5880","名稱":"合庫金","市場":"市","成交":"20.95","漲跌價":"-0.1","漲跌幅":"-0.48","成交張數":"15128","法人買賣日期":"08\/19","外資買進金額":"74.6","外資賣出金額":"200","外資買賣超金額":"-125","投信買進金額":"1.68","投信賣出金額":"0","投信買賣超金額":"+1.68","自營買進金額":"1.11","自營賣出金額":"6.06","自營買賣超金額":"-4.95","合計買進金額":"77.4","合計賣出金額":"206","合計買賣超金額":"-128","法人買賣超註記":"－  ＋  －"},{"排名":"120","代號":"8150","名稱":"南茂","市場":"市","成交":"54","漲跌價":"-1.2","漲跌幅":"-2.17","成交張數":"12248","法人買賣日期":"08\/19","外資買進金額":"246","外資賣出金額":"176","外資買賣超金額":"+70.4","投信買進金額":"1.64","投信賣出金額":"0","投信買賣超金額":"+1.64","自營買進金額":"23.1","自營賣出金額":"12.7","自營買賣超金額":"+10.4","合計買進金額":"271","合計賣出金額":"189","合計買賣超金額":"+82.4","法人買賣超註記":"＋  ＋  ＋"},{"排名":"121","代號":"2207","名稱":"和泰車","市場":"市","成交":"539","漲跌價":"-24","漲跌幅":"-4.26","成交張數":"522","法人買賣日期":"08\/19","外資買進金額":"51.1","外資賣出金額":"223","外資買賣超金額":"-172","投信買進金額":"1.63","投信賣出金額":"0","投信買賣超金額":"+1.63","自營買進金額":"4.9","自營賣出金額":"7.66","自營買賣超金額":"-2.76","合計買進金額":"57.6","合計賣出金額":"231","合計買賣超金額":"-173","法人買賣超註記":"－  ＋  －"},{"排名":"122","代號":"3036","名稱":"文曄","市場":"市","成交":"57.5","漲跌價":"-2.1","漲跌幅":"-3.52","成交張數":"3066","法人買賣日期":"08\/19","外資買進金額":"77.1","外資賣出金額":"34.1","外資買賣超金額":"+43","投信買進金額":"1.63","投信賣出金額":"0","投信買賣超金額":"+1.63","自營買進金額":"2.75","自營賣出金額":"2.94","自營買賣超金額":"-0.19","合計買進金額":"81.5","合計賣出金額":"37.1","合計買賣超金額":"+44.4","法人買賣超註記":"＋  ＋  －"},{"排名":"123","代號":"2880","名稱":"華南金","市場":"市","成交":"19.5","漲跌價":"-0.25","漲跌幅":"-1.27","成交張數":"19115","法人買賣日期":"08\/19","外資買進金額":"228","外資賣出金額":"164","外資買賣超金額":"+64.2","投信買進金額":"1.53","投信賣出金額":"0","投信買賣超金額":"+1.53","自營買進金額":"1.09","自營賣出金額":"4.89","自營買賣超金額":"-3.79","合計買進金額":"231","合計賣出金額":"169","合計買賣超金額":"+61.9","法人買賣超註記":"＋  ＋  －"},{"排名":"124","代號":"2887","名稱":"台新金","市場":"市","成交":"16.9","漲跌價":"-0.1","漲跌幅":"-0.59","成交張數":"20460","法人買賣日期":"08\/19","外資買進金額":"134","外資賣出金額":"159","外資買賣超金額":"-25.1","投信買進金額":"1.39","投信賣出金額":"0","投信買賣超金額":"+1.39","自營買進金額":"2.2","自營賣出金額":"5.25","自營買賣超金額":"-3.06","合計買進金額":"137","合計賣出金額":"164","合計買賣超金額":"-26.8","法人買賣超註記":"－  ＋  －"},{"排名":"125","代號":"6409","名稱":"旭隼","市場":"市","成交":"1295","漲跌價":"-20","漲跌幅":"-1.52","成交張數":"98","法人買賣日期":"08\/19","外資買進金額":"80.4","外資賣出金額":"93.1","外資買賣超金額":"-12.7","投信買進金額":"1.28","投信賣出金額":"0","投信買賣超金額":"+1.28","自營買進金額":"0","自營賣出金額":"1.28","自營買賣超金額":"-1.28","合計買進金額":"81.7","合計賣出金額":"94.4","合計買賣超金額":"-12.7","法人買賣超註記":"－  ＋  －"},{"排名":"126","代號":"4989","名稱":"榮科","市場":"市","成交":"40.3","漲跌價":"-2.65","漲跌幅":"-6.17","成交張數":"1589","法人買賣日期":"08\/19","外資買進金額":"15.4","外資賣出金額":"17.8","外資買賣超金額":"-2.44","投信買進金額":"1.12","投信賣出金額":"0","投信買賣超金額":"+1.12","自營買進金額":"0.25","自營賣出金額":"0","自營買賣超金額":"+0.25","合計買進金額":"16.7","合計賣出金額":"17.8","合計買賣超金額":"-1.07","法人買賣超註記":"－  ＋  ＋"},{"排名":"127","代號":"6716","名稱":"應廣","市場":"櫃","成交":"162.5","漲跌價":"-5.5","漲跌幅":"-3.27","成交張數":"489","法人買賣日期":"08\/19","外資買進金額":"5.86","外資賣出金額":"18.4","外資買賣超金額":"-12.6","投信買進金額":"1.03","投信賣出金額":"0","投信買賣超金額":"+1.03","自營買進金額":"0.17","自營賣出金額":"0","自營買賣超金額":"+0.17","合計買進金額":"7.06","合計賣出金額":"18.4","合計買賣超金額":"-11.4","法人買賣超註記":"－  ＋  ＋"},{"排名":"128","代號":"5876","名稱":"上海商銀","市場":"市","成交":"40.55","漲跌價":"-0.85","漲跌幅":"-2.05","成交張數":"4697","法人買賣日期":"08\/19","外資買進金額":"72.7","外資賣出金額":"151","外資買賣超金額":"-78","投信買進金額":"0.94","投信賣出金額":"0","投信買賣超金額":"+0.94","自營買進金額":"0.98","自營賣出金額":"4.33","自營買賣超金額":"-3.35","合計買進金額":"74.6","合計賣出金額":"155","合計買賣超金額":"-80.5","法人買賣超註記":"－  ＋  －"},{"排名":"129","代號":"3217","名稱":"優群","市場":"櫃","成交":"91.9","漲跌價":"-4.1","漲跌幅":"-4.27","成交張數":"384","法人買賣日期":"08\/19","外資買進金額":"5.59","外資賣出金額":"15.3","外資買賣超金額":"-9.68","投信買進金額":"0.93","投信賣出金額":"0","投信買賣超金額":"+0.93","自營買進金額":"0.37","自營賣出金額":"0.09","自營買賣超金額":"+0.28","合計買進金額":"6.89","合計賣出金額":"15.4","合計買賣超金額":"-8.47","法人買賣超註記":"－  ＋  ＋"},{"排名":"130","代號":"6505","名稱":"台塑化","市場":"市","成交":"91.1","漲跌價":"-3.3","漲跌幅":"-3.5","成交張數":"7811","法人買賣日期":"08\/19","外資買進金額":"207","外資賣出金額":"442","外資買賣超金額":"-235","投信買進金額":"0.83","投信賣出金額":"0","投信買賣超金額":"+0.83","自營買進金額":"16","自營賣出金額":"25.1","自營買賣超金額":"-9.11","合計買進金額":"224","合計賣出金額":"467","合計買賣超金額":"-243","法人買賣超註記":"－  ＋  －"},{"排名":"131","代號":"6147","名稱":"頎邦","市場":"櫃","成交":"73.1","漲跌價":"-1.9","漲跌幅":"-2.53","成交張數":"4820","法人買賣日期":"08\/19","外資買進金額":"224","外資賣出金額":"154","外資買賣超金額":"+69.8","投信買進金額":"0.81","投信賣出金額":"0","投信買賣超金額":"+0.81","自營買進金額":"5.64","自營賣出金額":"17.3","自營買賣超金額":"-11.7","合計買進金額":"230","合計賣出金額":"172","合計買賣超金額":"+58.9","法人買賣超註記":"＋  ＋  －"},{"排名":"132","代號":"9910","名稱":"豐泰","市場":"市","成交":"200.5","漲跌價":"-6.5","漲跌幅":"-3.14","成交張數":"1310","法人買賣日期":"08\/19","外資買進金額":"126","外資賣出金額":"140","外資買賣超金額":"-14.4","投信買進金額":"0.8","投信賣出金額":"0","投信買賣超金額":"+0.8","自營買進金額":"0.4","自營賣出金額":"3.88","自營買賣超金額":"-3.48","合計買進金額":"127","合計賣出金額":"144","合計買賣超金額":"-17.1","法人買賣超註記":"－  ＋  －"},{"排名":"133","代號":"2801","名稱":"彰銀","市場":"市","成交":"16.6","漲跌價":"-0.2","漲跌幅":"-1.19","成交張數":"7953","法人買賣日期":"08\/19","外資買進金額":"47.9","外資賣出金額":"95.5","外資買賣超金額":"-47.6","投信買進金額":"0.75","投信賣出金額":"0","投信買賣超金額":"+0.75","自營買進金額":"1.66","自營賣出金額":"2.86","自營買賣超金額":"-1.2","合計買進金額":"50.3","合計賣出金額":"98.3","合計買賣超金額":"-48","法人買賣超註記":"－  ＋  －"},{"排名":"134","代號":"006201","名稱":"元大富櫃50","市場":"櫃","成交":"20.07","漲跌價":"-0.41","漲跌幅":"-2","成交張數":"91","法人買賣日期":"08\/19","外資買進金額":"0","外資賣出金額":"0","外資買賣超金額":"0","投信買進金額":"0.65","投信賣出金額":"0","投信買賣超金額":"+0.65","自營買進金額":"0.08","自營賣出金額":"1.52","自營買賣超金額":"-1.44","合計買進金額":"0.73","合計賣出金額":"1.52","合計買賣超金額":"-0.79","法人買賣超註記":"・  ＋  －"},{"排名":"135","代號":"1476","名稱":"儒鴻","市場":"市","成交":"510","漲跌價":"-30","漲跌幅":"-5.56","成交張數":"1258","法人買賣日期":"08\/19","外資買進金額":"364","外資賣出金額":"421","外資買賣超金額":"-56.4","投信買進金額":"0.52","投信賣出金額":"0","投信買賣超金額":"+0.52","自營買進金額":"13.4","自營賣出金額":"24.2","自營買賣超金額":"-10.8","合計買進金額":"378","合計賣出金額":"445","合計買賣超金額":"-66.7","法人買賣超註記":"－  ＋  －"},{"排名":"136","代號":"3481","名稱":"群創","市場":"市","成交":"19.1","漲跌價":"-1.15","漲跌幅":"-5.68","成交張數":"214398","法人買賣日期":"08\/19","外資買進金額":"617","外資賣出金額":"1807","外資買賣超金額":"-1190","投信買進金額":"0.45","投信賣出金額":"0","投信買賣超金額":"+0.45","自營買進金額":"77.6","自營賣出金額":"156","自營買賣超金額":"-78.9","合計買進金額":"695","合計賣出金額":"1963","合計買賣超金額":"-1268","法人買賣超註記":"－  ＋  －"},{"排名":"137","代號":"3152","名稱":"璟德","市場":"櫃","成交":"448","漲跌價":"-9","漲跌幅":"-1.97","成交張數":"162","法人買賣日期":"08\/19","外資買進金額":"40.5","外資賣出金額":"14.8","外資買賣超金額":"+25.6","投信買進金額":"0.45","投信賣出金額":"0","投信買賣超金額":"+0.45","自營買進金額":"0","自營賣出金額":"0.66","自營買賣超金額":"-0.66","合計買進金額":"40.9","合計賣出金額":"15.5","合計買賣超金額":"+25.4","法人買賣超註記":"＋  ＋  －"},{"排名":"138","代號":"3023","名稱":"信邦","市場":"市","成交":"214","漲跌價":"-2","漲跌幅":"-0.93","成交張數":"721","法人買賣日期":"08\/19","外資買進金額":"86.2","外資賣出金額":"87.5","外資買賣超金額":"-1.28","投信買進金額":"1.95","投信賣出金額":"1.52","投信買賣超金額":"+0.43","自營買進金額":"0.87","自營賣出金額":"1.66","自營買賣超金額":"-0.79","合計買進金額":"89","合計賣出金額":"90.7","合計買賣超金額":"-1.63","法人買賣超註記":"－  ＋  －"},{"排名":"139","代號":"3374","名稱":"精材","市場":"櫃","成交":"135.5","漲跌價":"-6.5","漲跌幅":"-4.58","成交張數":"2922","法人買賣日期":"08\/19","外資買進金額":"63.2","外資賣出金額":"131","外資買賣超金額":"-67.7","投信買進金額":"1.64","投信賣出金額":"1.23","投信買賣超金額":"+0.41","自營買進金額":"4.28","自營賣出金額":"8.54","自營買賣超金額":"-4.26","合計買進金額":"69.1","合計賣出金額":"141","合計買賣超金額":"-71.5","法人買賣超註記":"－  ＋  －"},{"排名":"140","代號":"6121","名稱":"新普","市場":"櫃","成交":"310","漲跌價":"-3.5","漲跌幅":"-1.12","成交張數":"874","法人買賣日期":"08\/19","外資買進金額":"111","外資賣出金額":"166","外資買賣超金額":"-55.6","投信買進金額":"0.31","投信賣出金額":"0","投信買賣超金額":"+0.31","自營買進金額":"2.17","自營賣出金額":"2.23","自營買賣超金額":"-0.07","合計買進金額":"113","合計賣出金額":"168","合計買賣超金額":"-55.3","法人買賣超註記":"－  ＋  －"},{"排名":"141","代號":"3680","名稱":"家登","市場":"櫃","成交":"231.5","漲跌價":"-10.5","漲跌幅":"-4.34","成交張數":"330","法人買賣日期":"08\/19","外資買進金額":"10.5","外資賣出金額":"19.9","外資買賣超金額":"-9.36","投信買進金額":"0.23","投信賣出金額":"0","投信買賣超金額":"+0.23","自營買進金額":"0.47","自營賣出金額":"6.09","自營買賣超金額":"-5.62","合計買進金額":"11.2","合計賣出金額":"26","合計買賣超金額":"-14.7","法人買賣超註記":"－  ＋  －"},{"排名":"142","代號":"1477","名稱":"聚陽","市場":"市","成交":"216","漲跌價":"-10","漲跌幅":"-4.42","成交張數":"2297","法人買賣日期":"08\/19","外資買進金額":"272","外資賣出金額":"195","外資買賣超金額":"+76.8","投信買進金額":"0.43","投信賣出金額":"0.22","投信買賣超金額":"+0.22","自營買進金額":"14.1","自營賣出金額":"7.68","自營買賣超金額":"+6.4","合計買進金額":"287","合計賣出金額":"203","合計買賣超金額":"+83.4","法人買賣超註記":"＋  ＋  ＋"},{"排名":"143","代號":"3081","名稱":"聯亞","市場":"櫃","成交":"214","漲跌價":"-7","漲跌幅":"-3.17","成交張數":"440","法人買賣日期":"08\/19","外資買進金額":"21.8","外資賣出金額":"25.2","外資買賣超金額":"-3.45","投信買進金額":"0.22","投信賣出金額":"0","投信買賣超金額":"+0.22","自營買進金額":"1.29","自營賣出金額":"0.86","自營買賣超金額":"+0.43","合計買進金額":"23.3","合計賣出金額":"26.1","合計買賣超金額":"-2.8","法人買賣超註記":"－  ＋  ＋"},{"排名":"144","代號":"3413","名稱":"京鼎","市場":"市","成交":"210.5","漲跌價":"-9","漲跌幅":"-4.1","成交張數":"884","法人買賣日期":"08\/19","外資買進金額":"65.1","外資賣出金額":"87.3","外資買賣超金額":"-22.2","投信買進金額":"0.43","投信賣出金額":"0.21","投信買賣超金額":"+0.21","自營買進金額":"1.71","自營賣出金額":"3.29","自營買賣超金額":"-1.58","合計買進金額":"67.3","合計賣出金額":"90.9","合計買賣超金額":"-23.6","法人買賣超註記":"－  ＋  －"},{"排名":"145","代號":"1229","名稱":"聯華","市場":"市","成交":"49.9","漲跌價":"-0.9","漲跌幅":"-1.77","成交張數":"1610","法人買賣日期":"08\/19","外資買進金額":"7.53","外資賣出金額":"32.7","外資買賣超金額":"-25.2","投信買進金額":"0.2","投信賣出金額":"0","投信買賣超金額":"+0.2","自營買進金額":"0.7","自營賣出金額":"4.45","自營買賣超金額":"-3.75","合計買進金額":"8.43","合計賣出金額":"37.1","合計買賣超金額":"-28.7","法人買賣超註記":"－  ＋  －"},{"排名":"146","代號":"4743","名稱":"合一","市場":"櫃","成交":"185","漲跌價":"-4","漲跌幅":"-2.12","成交張數":"1668","法人買賣日期":"08\/19","外資買進金額":"39.5","外資賣出金額":"104","外資買賣超金額":"-64.5","投信買進金額":"0.19","投信賣出金額":"0","投信買賣超金額":"+0.19","自營買進金額":"2.23","自營賣出金額":"4.51","自營買賣超金額":"-2.29","合計買進金額":"41.9","合計賣出金額":"109","合計買賣超金額":"-66.6","法人買賣超註記":"－  ＋  －"},{"排名":"147","代號":"9941","名稱":"裕融","市場":"市","成交":"171","漲跌價":"-4","漲跌幅":"-2.29","成交張數":"769","法人買賣日期":"08\/19","外資買進金額":"7.93","外資賣出金額":"47.2","外資買賣超金額":"-39.3","投信買進金額":"0.17","投信賣出金額":"0","投信買賣超金額":"+0.17","自營買進金額":"0","自營賣出金額":"0.74","自營買賣超金額":"-0.74","合計買進金額":"8.1","合計賣出金額":"48","合計買賣超金額":"-39.9","法人買賣超註記":"－  ＋  －"},{"排名":"148","代號":"1722","名稱":"台肥","市場":"市","成交":"57.1","漲跌價":"-0.9","漲跌幅":"-1.55","成交張數":"1921","法人買賣日期":"08\/19","外資買進金額":"8.35","外資賣出金額":"51.4","外資買賣超金額":"-43","投信買進金額":"0.17","投信賣出金額":"0","投信買賣超金額":"+0.17","自營買進金額":"3.03","自營賣出金額":"4.13","自營買賣超金額":"-1.09","合計買進金額":"11.6","合計賣出金額":"55.5","合計買賣超金額":"-44","法人買賣超註記":"－  ＋  －"},{"排名":"149","代號":"2015","名稱":"豐興","市場":"市","成交":"75","漲跌價":"-0.8","漲跌幅":"-1.06","成交張數":"1362","法人買賣日期":"08\/19","外資買進金額":"20.8","外資賣出金額":"62.5","外資買賣超金額":"-41.7","投信買進金額":"0.15","投信賣出金額":"0","投信買賣超金額":"+0.15","自營買進金額":"0.15","自營賣出金額":"0.61","自營買賣超金額":"-0.46","合計買進金額":"21.1","合計賣出金額":"63.1","合計買賣超金額":"-42","法人買賣超註記":"－  ＋  －"},{"排名":"150","代號":"3706","名稱":"神達","市場":"市","成交":"27.1","漲跌價":"-0.5","漲跌幅":"-1.81","成交張數":"3104","法人買賣日期":"08\/19","外資買進金額":"7.44","外資賣出金額":"33.8","外資買賣超金額":"-26.3","投信買進金額":"0.14","投信賣出金額":"0","投信買賣超金額":"+0.14","自營買進金額":"0.25","自營賣出金額":"0.87","自營買賣超金額":"-0.63","合計買進金額":"7.82","合計賣出金額":"34.6","合計買賣超金額":"-26.8","法人買賣超註記":"－  ＋  －"},{"排名":"151","代號":"2888","名稱":"新光金","市場":"市","成交":"9.02","漲跌價":"-0.09","漲跌幅":"-0.99","成交張數":"45785","法人買賣日期":"08\/19","外資買進金額":"81.6","外資賣出金額":"132","外資買賣超金額":"-50.7","投信買進金額":"0.14","投信賣出金額":"0","投信買賣超金額":"+0.14","自營買進金額":"14.7","自營賣出金額":"10.1","自營買賣超金額":"+4.61","合計買進金額":"96.5","合計賣出金額":"142","合計買賣超金額":"-46","法人買賣超註記":"－  ＋  ＋"},{"排名":"152","代號":"5434","名稱":"崇越","市場":"市","成交":"128.5","漲跌價":"-2","漲跌幅":"-1.53","成交張數":"189","法人買賣日期":"08\/19","外資買進金額":"12.4","外資賣出金額":"10.6","外資買賣超金額":"+1.81","投信買進金額":"0.13","投信賣出金額":"0","投信買賣超金額":"+0.13","自營買進金額":"0","自營賣出金額":"0.13","自營買賣超金額":"-0.13","合計買進金額":"12.5","合計賣出金額":"10.7","合計買賣超金額":"+1.81","法人買賣超註記":"＋  ＋  －"},{"排名":"153","代號":"2823","名稱":"中壽","市場":"市","成交":"28.35","漲跌價":"-0.15","漲跌幅":"-0.53","成交張數":"27309","法人買賣日期":"08\/19","外資買進金額":"111","外資賣出金額":"233","外資買賣超金額":"-121","投信買進金額":"0.11","投信賣出金額":"0","投信買賣超金額":"+0.11","自營買進金額":"179","自營賣出金額":"14","自營買賣超金額":"+165","合計買進金額":"290","合計賣出金額":"247","合計買賣超金額":"+43.3","法人買賣超註記":"－  ＋  ＋"},{"排名":"154","代號":"1227","名稱":"佳格","市場":"市","成交":"51.7","漲跌價":"-0.2","漲跌幅":"-0.39","成交張數":"1023","法人買賣日期":"08\/19","外資買進金額":"7.6","外資賣出金額":"20.3","外資買賣超金額":"-12.7","投信買進金額":"0.1","投信賣出金額":"0","投信買賣超金額":"+0.1","自營買進金額":"0","自營賣出金額":"0.98","自營買賣超金額":"-0.98","合計買進金額":"7.7","合計賣出金額":"21.2","合計買賣超金額":"-13.5","法人買賣超註記":"－  ＋  －"},{"排名":"155","代號":"5471","名稱":"松翰","市場":"市","成交":"86.5","漲跌價":"-3.4","漲跌幅":"-3.78","成交張數":"2220","法人買賣日期":"08\/19","外資買進金額":"31.4","外資賣出金額":"72.6","外資買賣超金額":"-41.2","投信買進金額":"0.09","投信賣出金額":"0","投信買賣超金額":"+0.09","自營買進金額":"1.85","自營賣出金額":"3.48","自營買賣超金額":"-1.63","合計買進金額":"33.3","合計賣出金額":"76.1","合計買賣超金額":"-42.8","法人買賣超註記":"－  ＋  －"},{"排名":"156","代號":"1504","名稱":"東元","市場":"市","成交":"28.75","漲跌價":"-0.45","漲跌幅":"-1.54","成交張數":"3284","法人買賣日期":"08\/19","外資買進金額":"23.5","外資賣出金額":"71.8","外資買賣超金額":"-48.3","投信買進金額":"0.09","投信賣出金額":"0","投信買賣超金額":"+0.09","自營買進金額":"0.12","自營賣出金額":"1.34","自營買賣超金額":"-1.23","合計買進金額":"23.7","合計賣出金額":"73.1","合計買賣超金額":"-49.5","法人買賣超註記":"－  ＋  －"},{"排名":"157","代號":"6592","名稱":"和潤企業","市場":"市","成交":"81.3","漲跌價":"-1.1","漲跌幅":"-1.33","成交張數":"1485","法人買賣日期":"08\/19","外資買進金額":"18.2","外資賣出金額":"51.3","外資買賣超金額":"-33.1","投信買進金額":"0.08","投信賣出金額":"0","投信買賣超金額":"+0.08","自營買進金額":"0.65","自營賣出金額":"1.33","自營買賣超金額":"-0.68","合計買進金額":"18.9","合計賣出金額":"52.7","合計買賣超金額":"-33.7","法人買賣超註記":"－  ＋  －"},{"排名":"158","代號":"2353","名稱":"宏碁","市場":"市","成交":"24.45","漲跌價":"-0.95","漲跌幅":"-3.74","成交張數":"21728","法人買賣日期":"08\/19","外資買進金額":"131","外資賣出金額":"378","外資買賣超金額":"-247","投信買進金額":"0.07","投信賣出金額":"0","投信買賣超金額":"+0.07","自營買進金額":"2.42","自營賣出金額":"15.9","自營買賣超金額":"-13.5","合計買進金額":"133","合計賣出金額":"393","合計買賣超金額":"-260","法人買賣超註記":"－  ＋  －"},{"排名":"159","代號":"2451","名稱":"創見","市場":"市","成交":"67.1","漲跌價":"-1.1","漲跌幅":"-1.61","成交張數":"978","法人買賣日期":"08\/19","外資買進金額":"7.8","外資賣出金額":"29.8","外資買賣超金額":"-22","投信買進金額":"0.07","投信賣出金額":"0","投信買賣超金額":"+0.07","自營買進金額":"0.2","自營賣出金額":"0.77","自營買賣超金額":"-0.57","合計買進金額":"8.06","合計賣出金額":"30.5","合計買賣超金額":"-22.5","法人買賣超註記":"－  ＋  －"},{"排名":"160","代號":"2889","名稱":"國票金","市場":"市","成交":"15.85","漲跌價":"-0.15","漲跌幅":"-0.94","成交張數":"2930","法人買賣日期":"08\/19","外資買進金額":"8.67","外資賣出金額":"13.3","外資買賣超金額":"-4.6","投信買進金額":"0.06","投信賣出金額":"0","投信買賣超金額":"+0.06","自營買進金額":"0.05","自營賣出金額":"0.83","自營買賣超金額":"-0.78","合計買進金額":"8.78","合計賣出金額":"14.1","合計買賣超金額":"-5.32","法人買賣超註記":"－  ＋  －"},{"排名":"161","代號":"2812","名稱":"台中銀","市場":"市","成交":"11.85","漲跌價":"-0.05","漲跌幅":"-0.42","成交張數":"6933","法人買賣日期":"08\/19","外資買進金額":"17.5","外資賣出金額":"3.72","外資買賣超金額":"+13.7","投信買進金額":"0.06","投信賣出金額":"0","投信買賣超金額":"+0.06","自營買進金額":"0.05","自營賣出金額":"0.73","自營買賣超金額":"-0.68","合計買進金額":"17.6","合計賣出金額":"4.44","合計買賣超金額":"+13.1","法人買賣超註記":"＋  ＋  －"},{"排名":"162","代號":"6005","名稱":"群益證","市場":"市","成交":"15","漲跌價":"-0.35","漲跌幅":"-2.28","成交張數":"4659","法人買賣日期":"08\/19","外資買進金額":"19.8","外資賣出金額":"33.2","外資買賣超金額":"-13.4","投信買進金額":"0.05","投信賣出金額":"0","投信買賣超金額":"+0.05","自營買進金額":"0","自營賣出金額":"0","自營買賣超金額":"0","合計買進金額":"19.9","合計賣出金額":"33.2","合計買賣超金額":"-13.3","法人買賣超註記":"－  ＋  ・"},{"排名":"163","代號":"8112","名稱":"至上","市場":"市","成交":"42.3","漲跌價":"-1.15","漲跌幅":"-2.65","成交張數":"3077","法人買賣日期":"08\/19","外資買進金額":"14.3","外資賣出金額":"60.3","外資買賣超金額":"-46","投信買進金額":"0.04","投信賣出金額":"0","投信買賣超金額":"+0.04","自營買進金額":"0.68","自營賣出金額":"0.79","自營買賣超金額":"-0.11","合計買進金額":"15","合計賣出金額":"61","合計買賣超金額":"-46","法人買賣超註記":"－  ＋  －"},{"排名":"164","代號":"1904","名稱":"正隆","市場":"市","成交":"35.8","漲跌價":"-0.95","漲跌幅":"-2.59","成交張數":"3714","法人買賣日期":"08\/19","外資買進金額":"28","外資賣出金額":"70","外資買賣超金額":"-42","投信買進金額":"0.04","投信賣出金額":"0","投信買賣超金額":"+0.04","自營買進金額":"2.22","自營賣出金額":"2.78","自營買賣超金額":"-0.56","合計買進金額":"30.2","合計賣出金額":"72.8","合計買賣超金額":"-42.5","法人買賣超註記":"－  ＋  －"},{"排名":"165","代號":"2838","名稱":"聯邦銀","市場":"市","成交":"11.75","漲跌價":"-0.1","漲跌幅":"-0.84","成交張數":"1897","法人買賣日期":"08\/19","外資買進金額":"4.57","外資賣出金額":"5.16","外資買賣超金額":"-0.59","投信買進金額":"0.04","投信賣出金額":"0","投信買賣超金額":"+0.04","自營買進金額":"0.04","自營賣出金額":"0.78","自營買賣超金額":"-0.74","合計買進金額":"4.64","合計賣出金額":"5.93","合計買賣超金額":"-1.29","法人買賣超註記":"－  ＋  －"},{"排名":"166","代號":"2820","名稱":"華票","市場":"市","成交":"16.1","漲跌價":"-0.15","漲跌幅":"-0.92","成交張數":"884","法人買賣日期":"08\/19","外資買進金額":"2.79","外資賣出金額":"6.62","外資買賣超金額":"-3.83","投信買進金額":"0.03","投信賣出金額":"0","投信買賣超金額":"+0.03","自營買進金額":"0.02","自營賣出金額":"0.4","自營買賣超金額":"-0.39","合計買進金額":"2.84","合計賣出金額":"7.02","合計買賣超金額":"-4.18","法人買賣超註記":"－  ＋  －"},{"排名":"167","代號":"2851","名稱":"中再保","市場":"市","成交":"26.1","漲跌價":"-0.75","漲跌幅":"-2.79","成交張數":"965","法人買賣日期":"08\/19","外資買進金額":"1.44","外資賣出金額":"12","外資買賣超金額":"-10.5","投信買進金額":"0.03","投信賣出金額":"0","投信買賣超金額":"+0.03","自營買進金額":"0.45","自營賣出金額":"0.38","自營買賣超金額":"+0.07","合計買進金額":"1.92","合計賣出金額":"12.3","合計買賣超金額":"-10.4","法人買賣超註記":"－  ＋  ＋"},{"排名":"168","代號":"2855","名稱":"統一證","市場":"市","成交":"25.6","漲跌價":"-0.2","漲跌幅":"-0.78","成交張數":"2998","法人買賣日期":"08\/19","外資買進金額":"24","外資賣出金額":"33.5","外資買賣超金額":"-9.42","投信買進金額":"0.03","投信賣出金額":"0","投信買賣超金額":"+0.03","自營買進金額":"0","自營賣出金額":"0","自營買賣超金額":"0","合計買進金額":"24.1","合計賣出金額":"33.5","合計買賣超金額":"-9.4","法人買賣超註記":"－  ＋  ・"},{"排名":"169","代號":"1103","名稱":"嘉泥","市場":"市","成交":"20.75","漲跌價":"-0.45","漲跌幅":"-2.12","成交張數":"1012","法人買賣日期":"08\/19","外資買進金額":"1.66","外資賣出金額":"11.6","外資買賣超金額":"-9.94","投信買進金額":"0.02","投信賣出金額":"0","投信買賣超金額":"+0.02","自營買進金額":"2.42","自營賣出金額":"0.46","自營買賣超金額":"+1.96","合計買進金額":"4.11","合計賣出金額":"12.1","合計買賣超金額":"-7.96","法人買賣超註記":"－  ＋  ＋"}]